[
  {
    "Type": "MouseMove",
    "Time": 0,
    "X": 578,
    "Y": 606
  },
  {
    "Type": "MouseMove",
    "Time": 25,
    "X": 579,
    "Y": 604
  },
  {
    "Type": "MouseMove",
    "Time": 50,
    "X": 576,
    "Y": 608
  },
  {
    "Type": "MouseMove",
    "Time": 75,
    "X": 576,
    "Y": 606
  },
  {
    "Type": "MouseMove",
    "Time": 103,
    "X": 576,
    "Y": 606,
    "Delta": null,
    "KeyCode": null
  },
  {
    "Type": "MouseMove",
    "Time": 122,
    "X": 579,
    "Y": 600,
    "Delta": null,
    "KeyCode": null
  },
  {
    "Type": "MouseMove",
    "Time": 143,
    "X": 591,
    "Y": 591,
    "Delta": null,
    "KeyCode": null
  },
  {
    "Type": "MouseMove",
    "Time": 32,
    "X": 595,
    "Y": 591
  },
  {
    "Type": "MouseMove",
    "Time": 71,
    "X": 599,
    "Y": 591
  },
  {
    "Type": "MouseMove",
    "Time": 110,
    "X": 597,
    "Y": 588
  },
  {
    "Type": "MouseMove",
    "Time": 150,
    "X": 597,
    "Y": 588,
    "Delta": null,
    "KeyCode": null
  },
  {
    "Type": "MouseMove",
    "Time": 164,
    "X": 603,
    "Y": 588,
    "Delta": null,
    "KeyCode": null
  },
  {
    "Type": "MouseMove",
    "Time": 2,
    "X": 619,
    "Y": 577
  },
  {
    "Type": "MouseMove",
    "Time": 60,
    "X": 615,
    "Y": 579
  },
  {
    "Type": "MouseMove",
    "Time": 118,
    "X": 618,
    "Y": 579
  },
  {
    "Type": "MouseMove",
    "Time": 177,
    "X": 618,
    "Y": 579,
    "Delta": null,
    "KeyCode": null
  },
  {
    "Type": "MouseMove",
    "Time": 61,
    "X": 643,
    "Y": 573
  },
  {
    "Type": "MouseMove",
    "Time": 95,
    "X": 646,
    "Y": 568
  },
  {
    "Type": "MouseMove",
    "Time": 129,
    "X": 647,
    "Y": 569
  },
  {
    "Type": "MouseMove",
    "Time": 163,
    "X": 645,
    "Y": 570
  },
  {
    "Type": "MouseMove",
    "Time": 199,
    "X": 645,
    "Y": 570,
    "Delta": null,
    "KeyCode": null
  },
  {
    "Type": "MouseMove",
    "Time": 223,
    "X": 669,
    "Y": 561,
    "Delta": null,
    "KeyCode": null
  },
  {
    "Type": "MouseMove",
    "Time": 245,
    "X": 690,
    "Y": 555,
    "Delta": null,
    "KeyCode": null
  },
  {
    "Type": "MouseMove",
    "Time": 248,
    "X": 696,
    "Y": 552,
    "Delta": null,
    "KeyCode": null
  },
  {
    "Type": "MouseMove",
    "Time": 256,
    "X": 705,
    "Y": 552,
    "Delta": null,
    "KeyCode": null
  },
  {
    "Type": "MouseMove",
    "Time": 113,
    "X": 715,
    "Y": 546
  },
  {
    "Type": "MouseMove",
    "Time": 167,
    "X": 714,
    "Y": 547
  },
  {
    "Type": "MouseMove",
    "Time": 221,
    "X": 714,
    "Y": 546
  },
  {
    "Type": "MouseMove",
    "Time": 275,
    "X": 714,
    "Y": 546,
    "Delta": null,
    "KeyCode": null
  },
  {
    "Type": "MouseMove",
    "Time": 280,
    "X": 726,
    "Y": 543,
    "Delta": null,
    "KeyCode": null
  },
  {
    "Type": "MouseMove",
    "Time": 291,
    "X": 732,
    "Y": 540,
    "Delta": null,
    "KeyCode": null
  },
  {
    "Type": "MouseMove",
    "Time": 301,
    "X": 738,
    "Y": 540,
    "Delta": null,
    "KeyCode": null
  },
  {
    "Type": "MouseMove",
    "Time": 320,
    "X": 759,
    "Y": 531,
    "Delta": null,
    "KeyCode": null
  },
  {
    "Type": "MouseMove",
    "Time": 342,
    "X": 774,
    "Y": 525,
    "Delta": null,
    "KeyCode": null
  },
  {
    "Type": "MouseMove",
    "Time": 363,
    "X": 789,
    "Y": 519,
    "Delta": null,
    "KeyCode": null
  },
  {
    "Type": "MouseMove",
    "Time": 372,
    "X": 792,
    "Y": 516,
    "Delta": null,
    "KeyCode": null
  },
  {
    "Type": "MouseMove",
    "Time": 384,
    "X": 795,
    "Y": 516,
    "Delta": null,
    "KeyCode": null
  },
  {
    "Type": "MouseMove",
    "Time": 392,
    "X": 798,
    "Y": 513,
    "Delta": null,
    "KeyCode": null
  },
  {
    "Type": "MouseMove",
    "Time": 400,
    "X": 801,
    "Y": 510,
    "Delta": null,
    "KeyCode": null
  },
  {
    "Type": "MouseMove",
    "Time": 416,
    "X": 804,
    "Y": 507,
    "Delta": null,
    "KeyCode": null
  },
  {
    "Type": "MouseMove",
    "Time": 427,
    "X": 810,
    "Y": 504,
    "Delta": null,
    "KeyCode": null
  },
  {
    "Type": "MouseMove",
    "Time": 445,
    "X": 822,
    "Y": 495,
    "Delta": null,
    "KeyCode": null
  },
  {
    "Type": "MouseMove",
    "Time": 465,
    "X": 831,
    "Y": 489,
    "Delta": null,
    "KeyCode": null
  },
  {
    "Type": "MouseMove",
    "Time": 475,
    "X": 834,
    "Y": 486,
    "Delta": null,
    "KeyCode": null
  },
  {
    "Type": "MouseMove",
    "Time": 486,
    "X": 837,
    "Y": 486,
    "Delta": null,
    "KeyCode": null
  },
  {
    "Type": "MouseMove",
    "Time": 508,
    "X": 840,
    "Y": 483,
    "Delta": null,
    "KeyCode": null
  },
  {
    "Type": "MouseMove",
    "Time": 530,
    "X": 840,
    "Y": 480,
    "Delta": null,
    "KeyCode": null
  },
  {
    "Type": "MouseMove",
    "Time": 550,
    "X": 843,
    "Y": 477,
    "Delta": null,
    "KeyCode": null
  },
  {
    "Type": "MouseMove",
    "Time": 571,
    "X": 846,
    "Y": 471,
    "Delta": null,
    "KeyCode": null
  },
  {
    "Type": "MouseMove",
    "Time": 578,
    "X": 849,
    "Y": 471,
    "Delta": null,
    "KeyCode": null
  },
  {
    "Type": "MouseMove",
    "Time": 586,
    "X": 849,
    "Y": 468,
    "Delta": null,
    "KeyCode": null
  },
  {
    "Type": "MouseMove",
    "Time": 602,
    "X": 852,
    "Y": 468,
    "Delta": null,
    "KeyCode": null
  },
  {
    "Type": "MouseMove",
    "Time": 634,
    "X": 855,
    "Y": 465,
    "Delta": null,
    "KeyCode": null
  },
  {
    "Type": "MouseMove",
    "Time": 653,
    "X": 858,
    "Y": 462,
    "Delta": null,
    "KeyCode": null
  },
  {
    "Type": "MouseMove",
    "Time": 673,
    "X": 861,
    "Y": 459,
    "Delta": null,
    "KeyCode": null
  },
  {
    "Type": "MouseMove",
    "Time": 692,
    "X": 864,
    "Y": 453,
    "Delta": null,
    "KeyCode": null
  },
  {
    "Type": "MouseMove",
    "Time": 706,
    "X": 864,
    "Y": 450,
    "Delta": null,
    "KeyCode": null
  },
  {
    "Type": "MouseMove",
    "Time": 732,
    "X": 867,
    "Y": 450,
    "Delta": null,
    "KeyCode": null
  },
  {
    "Type": "MouseMove",
    "Time": 782,
    "X": 873,
    "Y": 444,
    "Delta": null,
    "KeyCode": null
  },
  {
    "Type": "MouseMove",
    "Time": 802,
    "X": 876,
    "Y": 444,
    "Delta": null,
    "KeyCode": null
  },
  {
    "Type": "MouseMove",
    "Time": 822,
    "X": 876,
    "Y": 441,
    "Delta": null,
    "KeyCode": null
  },
  {
    "Type": "MouseMove",
    "Time": 883,
    "X": 879,
    "Y": 438,
    "Delta": null,
    "KeyCode": null
  },
  {
    "Type": "MouseMove",
    "Time": 895,
    "X": 879,
    "Y": 435,
    "Delta": null,
    "KeyCode": null
  },
  {
    "Type": "MouseMove",
    "Time": 907,
    "X": 882,
    "Y": 435,
    "Delta": null,
    "KeyCode": null
  },
  {
    "Type": "MouseMove",
    "Time": 927,
    "X": 882,
    "Y": 432,
    "Delta": null,
    "KeyCode": null
  },
  {
    "Type": "DragStart",
    "Time": 1289,
    "X": 882,
    "Y": 432,
    "Delta": null,
    "KeyCode": null
  },
  {
    "Type": "MouseMove",
    "Time": 1364,
    "X": 885,
    "Y": 432,
    "Delta": null,
    "KeyCode": null
  },
  {
    "Type": "DragEnd",
    "Time": 1397,
    "X": 885,
    "Y": 432,
    "Delta": null,
    "KeyCode": null
  },
  {
    "Type": "MouseMove",
    "Time": 1421,
    "X": 888,
    "Y": 432,
    "Delta": null,
    "KeyCode": null
  },
  {
    "Type": "MouseMove",
    "Time": 1479,
    "X": 891,
    "Y": 432,
    "Delta": null,
    "KeyCode": null
  },
  {
    "Type": "MouseMove",
    "Time": 1511,
    "X": 894,
    "Y": 432,
    "Delta": null,
    "KeyCode": null
  },
  {
    "Type": "MouseMove",
    "Time": 1568,
    "X": 897,
    "Y": 432,
    "Delta": null,
    "KeyCode": null
  },
  {
    "Type": "DragStart",
    "Time": 1622,
    "X": 897,
    "Y": 432,
    "Delta": null,
    "KeyCode": null
  },
  {
    "Type": "DragEnd",
    "Time": 1705,
    "X": 897,
    "Y": 432,
    "Delta": null,
    "KeyCode": null
  },
  {
    "Type": "MouseMove",
    "Time": 2185,
    "X": 897,
    "Y": 435,
    "Delta": null,
    "KeyCode": null
  },
  {
    "Type": "MouseMove",
    "Time": 2217,
    "X": 897,
    "Y": 438,
    "Delta": null,
    "KeyCode": null
  },
  {
    "Type": "MouseMove",
    "Time": 2655,
    "X": 897,
    "Y": 435,
    "Delta": null,
    "KeyCode": null
  },
  {
    "Type": "MouseMove",
    "Time": 2676,
    "X": 897,
    "Y": 432,
    "Delta": null,
    "KeyCode": null
  },
  {
    "Type": "MouseMove",
    "Time": 3457,
    "X": 897,
    "Y": 429,
    "Delta": null,
    "KeyCode": null
  },
  {
    "Type": "MouseMove",
    "Time": 3548,
    "X": 897,
    "Y": 426,
    "Delta": null,
    "KeyCode": null
  },
  {
    "Type": "DragStart",
    "Time": 3722,
    "X": 897,
    "Y": 426,
    "Delta": null,
    "KeyCode": null
  },
  {
    "Type": "DragEnd",
    "Time": 3769,
    "X": 897,
    "Y": 426,
    "Delta": null,
    "KeyCode": null
  },
  {
    "Type": "DragStart",
    "Time": 4003,
    "X": 897,
    "Y": 426,
    "Delta": null,
    "KeyCode": null
  },
  {
    "Type": "DragEnd",
    "Time": 4099,
    "X": 897,
    "Y": 426,
    "Delta": null,
    "KeyCode": null
  },
  {
    "Type": "MouseMove",
    "Time": 6960,
    "X": 892,
    "Y": 428
  },
  {
    "Type": "MouseMove",
    "Time": 7009,
    "X": 895,
    "Y": 425
  },
  {
    "Type": "MouseMove",
    "Time": 7058,
    "X": 894,
    "Y": 426
  },
  {
    "Type": "MouseMove",
    "Time": 7109,
    "X": 894,
    "Y": 426,
    "Delta": null,
    "KeyCode": null
  },
  {
    "Type": "MouseMove",
    "Time": 7014,
    "X": 890,
    "Y": 430
  },
  {
    "Type": "MouseMove",
    "Time": 7045,
    "X": 885,
    "Y": 431
  },
  {
    "Type": "MouseMove",
    "Time": 7076,
    "X": 891,
    "Y": 427
  },
  {
    "Type": "MouseMove",
    "Time": 7107,
    "X": 888,
    "Y": 429
  },
  {
    "Type": "MouseMove",
    "Time": 7139,
    "X": 888,
    "Y": 429,
    "Delta": null,
    "KeyCode": null
  },
  {
    "Type": "MouseMove",
    "Time": 7162,
    "X": 876,
    "Y": 435,
    "Delta": null,
    "KeyCode": null
  },
  {
    "Type": "MouseMove",
    "Time": 7186,
    "X": 861,
    "Y": 444,
    "Delta": null,
    "KeyCode": null
  },
  {
    "Type": "MouseMove",
    "Time": 7209,
    "X": 840,
    "Y": 453,
    "Delta": null,
    "KeyCode": null
  },
  {
    "Type": "MouseMove",
    "Time": 7210,
    "X": 834,
    "Y": 459,
    "Delta": null,
    "KeyCode": null
  },
  {
    "Type": "MouseMove",
    "Time": 7042,
    "X": 810,
    "Y": 467
  },
  {
    "Type": "MouseMove",
    "Time": 7089,
    "X": 811,
    "Y": 465
  },
  {
    "Type": "MouseMove",
    "Time": 7136,
    "X": 811,
    "Y": 465
  },
  {
    "Type": "MouseMove",
    "Time": 7183,
    "X": 813,
    "Y": 465
  },
  {
    "Type": "MouseMove",
    "Time": 7233,
    "X": 813,
    "Y": 465,
    "Delta": null,
    "KeyCode": null
  },
  {
    "Type": "MouseMove",
    "Time": 7234,
    "X": 804,
    "Y": 468,
    "Delta": null,
    "KeyCode": null
  },
  {
    "Type": "MouseMove",
    "Time": 7073,
    "X": 795,
    "Y": 470
  },
  {
    "Type": "MouseMove",
    "Time": 7115,
    "X": 792,
    "Y": 469
  },
  {
    "Type": "MouseMove",
    "Time": 7157,
    "X": 797,
    "Y": 470
  },
  {
    "Type": "MouseMove",
    "Time": 7199,
    "X": 795,
    "Y": 471
  },
  {
    "Type": "MouseMove",
    "Time": 7242,
    "X": 795,
    "Y": 471,
    "Delta": null,
    "KeyCode": null
  },
  {
    "Type": "MouseMove",
    "Time": 7101,
    "X": 780,
    "Y": 476
  },
  {
    "Type": "MouseMove",
    "Time": 7138,
    "X": 782,
    "Y": 474
  },
  {
    "Type": "MouseMove",
    "Time": 7175,
    "X": 782,
    "Y": 477
  },
  {
    "Type": "MouseMove",
    "Time": 7212,
    "X": 783,
    "Y": 477
  },
  {
    "Type": "MouseMove",
    "Time": 7250,
    "X": 783,
    "Y": 477,
    "Delta": null,
    "KeyCode": null
  },
  {
    "Type": "MouseMove",
    "Time": 7087,
    "X": 772,
    "Y": 479
  },
  {
    "Type": "MouseMove",
    "Time": 8496,
    "X": 773,
    "Y": 483
  },
  {
    "Type": "MouseMove",
    "Time": 8553,
    "X": 774,
    "Y": 480
  },
  {
    "Type": "MouseMove",
    "Time": 8610,
    "X": 774,
    "Y": 480,
    "Delta": null,
    "KeyCode": null
  },
  {
    "Type": "MouseMove",
    "Time": 8456,
    "X": 760,
    "Y": 487
  },
  {
    "Type": "MouseMove",
    "Time": 8500,
    "X": 760,
    "Y": 484
  },
  {
    "Type": "MouseMove",
    "Time": 8544,
    "X": 761,
    "Y": 487
  },
  {
    "Type": "MouseMove",
    "Time": 8588,
    "X": 759,
    "Y": 486
  },
  {
    "Type": "MouseMove",
    "Time": 8634,
    "X": 759,
    "Y": 486,
    "Delta": null,
    "KeyCode": null
  },
  {
    "Type": "MouseMove",
    "Time": 8446,
    "X": 748,
    "Y": 492
  },
  {
    "Type": "MouseMove",
    "Time": 8509,
    "X": 750,
    "Y": 489
  },
  {
    "Type": "MouseMove",
    "Time": 8572,
    "X": 747,
    "Y": 489
  },
  {
    "Type": "MouseMove",
    "Time": 8635,
    "X": 747,
    "Y": 489,
    "Delta": null,
    "KeyCode": null
  },
  {
    "Type": "MouseMove",
    "Time": 8657,
    "X": 723,
    "Y": 504,
    "Delta": null,
    "KeyCode": null
  },
  {
    "Type": "MouseMove",
    "Time": 8658,
    "X": 714,
    "Y": 507,
    "Delta": null,
    "KeyCode": null
  },
  {
    "Type": "MouseMove",
    "Time": 8680,
    "X": 696,
    "Y": 516,
    "Delta": null,
    "KeyCode": null
  },
  {
    "Type": "MouseMove",
    "Time": 8682,
    "X": 690,
    "Y": 519,
    "Delta": null,
    "KeyCode": null
  },
  {
    "Type": "MouseMove",
    "Time": 8560,
    "X": 687,
    "Y": 522
  },
  {
    "Type": "MouseMove",
    "Time": 8603,
    "X": 682,
    "Y": 522
  },
  {
    "Type": "MouseMove",
    "Time": 8646,
    "X": 684,
    "Y": 522
  },
  {
    "Type": "MouseMove",
    "Time": 8690,
    "X": 684,
    "Y": 522,
    "Delta": null,
    "KeyCode": null
  },
  {
    "Type": "MouseMove",
    "Time": 8698,
    "X": 678,
    "Y": 528,
    "Delta": null,
    "KeyCode": null
  },
  {
    "Type": "MouseMove",
    "Time": 8706,
    "X": 669,
    "Y": 531,
    "Delta": null,
    "KeyCode": null
  },
  {
    "Type": "MouseMove",
    "Time": 8557,
    "X": 657,
    "Y": 540
  },
  {
    "Type": "MouseMove",
    "Time": 8600,
    "X": 662,
    "Y": 540
  },
  {
    "Type": "MouseMove",
    "Time": 8643,
    "X": 660,
    "Y": 536
  },
  {
    "Type": "MouseMove",
    "Time": 8686,
    "X": 660,
    "Y": 537
  },
  {
    "Type": "MouseMove",
    "Time": 8729,
    "X": 660,
    "Y": 537,
    "Delta": null,
    "KeyCode": null
  },
  {
    "Type": "MouseMove",
    "Time": 8590,
    "X": 657,
    "Y": 537
  },
  {
    "Type": "MouseMove",
    "Time": 8625,
    "X": 654,
    "Y": 538
  },
  {
    "Type": "MouseMove",
    "Time": 8660,
    "X": 655,
    "Y": 538
  },
  {
    "Type": "MouseMove",
    "Time": 8695,
    "X": 654,
    "Y": 540
  },
  {
    "Type": "MouseMove",
    "Time": 8730,
    "X": 654,
    "Y": 540,
    "Delta": null,
    "KeyCode": null
  },
  {
    "Type": "MouseMove",
    "Time": 8738,
    "X": 648,
    "Y": 543,
    "Delta": null,
    "KeyCode": null
  },
  {
    "Type": "MouseMove",
    "Time": 8644,
    "X": 642,
    "Y": 555
  },
  {
    "Type": "MouseMove",
    "Time": 8683,
    "X": 645,
    "Y": 555
  },
  {
    "Type": "MouseMove",
    "Time": 8722,
    "X": 642,
    "Y": 552
  },
  {
    "Type": "MouseMove",
    "Time": 8763,
    "X": 642,
    "Y": 552,
    "Delta": null,
    "KeyCode": null
  },
  {
    "Type": "MouseMove",
    "Time": 8604,
    "X": 641,
    "Y": 554
  },
  {
    "Type": "MouseMove",
    "Time": 8665,
    "X": 640,
    "Y": 549
  },
  {
    "Type": "MouseMove",
    "Time": 8726,
    "X": 639,
    "Y": 552
  },
  {
    "Type": "MouseMove",
    "Time": 8787,
    "X": 639,
    "Y": 552,
    "Delta": null,
    "KeyCode": null
  },
  {
    "Type": "MouseMove",
    "Time": 8632,
    "X": 640,
    "Y": 553
  },
  {
    "Type": "MouseMove",
    "Time": 8686,
    "X": 637,
    "Y": 556
  },
  {
    "Type": "MouseMove",
    "Time": 8740,
    "X": 639,
    "Y": 555
  },
  {
    "Type": "MouseMove",
    "Time": 8794,
    "X": 639,
    "Y": 555,
    "Delta": null,
    "KeyCode": null
  },
  {
    "Type": "MouseMove",
    "Time": 8802,
    "X": 636,
    "Y": 558,
    "Delta": null,
    "KeyCode": null
  },
  {
    "Type": "MouseMove",
    "Time": 8818,
    "X": 633,
    "Y": 561,
    "Delta": null,
    "KeyCode": null
  },
  {
    "Type": "MouseMove",
    "Time": 8847,
    "X": 624,
    "Y": 573,
    "Delta": null,
    "KeyCode": null
  },
  {
    "Type": "MouseMove",
    "Time": 8708,
    "X": 619,
    "Y": 573
  },
  {
    "Type": "MouseMove",
    "Time": 8748,
    "X": 623,
    "Y": 573
  },
  {
    "Type": "MouseMove",
    "Time": 8788,
    "X": 619,
    "Y": 573
  },
  {
    "Type": "MouseMove",
    "Time": 8828,
    "X": 621,
    "Y": 576
  },
  {
    "Type": "MouseMove",
    "Time": 8868,
    "X": 621,
    "Y": 576,
    "Delta": null,
    "KeyCode": null
  },
  {
    "Type": "MouseMove",
    "Time": 8749,
    "X": 620,
    "Y": 576
  },
  {
    "Type": "MouseMove",
    "Time": 8798,
    "X": 618,
    "Y": 581
  },
  {
    "Type": "MouseMove",
    "Time": 8847,
    "X": 621,
    "Y": 579
  },
  {
    "Type": "MouseMove",
    "Time": 8897,
    "X": 621,
    "Y": 579,
    "Delta": null,
    "KeyCode": null
  },
  {
    "Type": "MouseMove",
    "Time": 8716,
    "X": 615,
    "Y": 584
  },
  {
    "Type": "MouseMove",
    "Time": 8762,
    "X": 616,
    "Y": 583
  },
  {
    "Type": "MouseMove",
    "Time": 8808,
    "X": 616,
    "Y": 584
  },
  {
    "Type": "MouseMove",
    "Time": 8854,
    "X": 618,
    "Y": 582
  },
  {
    "Type": "MouseMove",
    "Time": 8900,
    "X": 618,
    "Y": 582,
    "Delta": null,
    "KeyCode": null
  },
  {
    "Type": "MouseMove",
    "Time": 8908,
    "X": 618,
    "Y": 585,
    "Delta": null,
    "KeyCode": null
  },
  {
    "Type": "MouseMove",
    "Time": 8932,
    "X": 612,
    "Y": 588,
    "Delta": null,
    "KeyCode": null
  },
  {
    "Type": "MouseMove",
    "Time": 8850,
    "X": 607,
    "Y": 594
  },
  {
    "Type": "MouseMove",
    "Time": 8884,
    "X": 606,
    "Y": 593
  },
  {
    "Type": "MouseMove",
    "Time": 8918,
    "X": 609,
    "Y": 591
  },
  {
    "Type": "MouseMove",
    "Time": 8954,
    "X": 609,
    "Y": 591,
    "Delta": null,
    "KeyCode": null
  },
  {
    "Type": "MouseMove",
    "Time": 8956,
    "X": 609,
    "Y": 594,
    "Delta": null,
    "KeyCode": null
  },
  {
    "Type": "MouseMove",
    "Time": 9009,
    "X": 603,
    "Y": 600,
    "Delta": null,
    "KeyCode": null
  },
  {
    "Type": "MouseMove",
    "Time": 9033,
    "X": 594,
    "Y": 609,
    "Delta": null,
    "KeyCode": null
  },
  {
    "Type": "MouseMove",
    "Time": 8896,
    "X": 591,
    "Y": 607
  },
  {
    "Type": "MouseMove",
    "Time": 8942,
    "X": 592,
    "Y": 607
  },
  {
    "Type": "MouseMove",
    "Time": 8988,
    "X": 591,
    "Y": 609
  },
  {
    "Type": "MouseMove",
    "Time": 9036,
    "X": 591,
    "Y": 609,
    "Delta": null,
    "KeyCode": null
  },
  {
    "Type": "MouseMove",
    "Time": 8923,
    "X": 587,
    "Y": 606
  },
  {
    "Type": "MouseMove",
    "Time": 10536,
    "X": 585,
    "Y": 611
  },
  {
    "Type": "MouseMove",
    "Time": 10566,
    "X": 591,
    "Y": 611
  },
  {
    "Type": "MouseMove",
    "Time": 10596,
    "X": 588,
    "Y": 609
  },
  {
    "Type": "MouseMove",
    "Time": 10627,
    "X": 588,
    "Y": 609,
    "Delta": null,
    "KeyCode": null
  },
  {
    "Type": "MouseMove",
    "Time": 14402,
    "X": 588,
    "Y": 609
  },
  {
    "Type": "MouseMove",
    "Time": 14420,
    "X": 605,
    "Y": 602
  },
  {
    "Type": "MouseMove",
    "Time": 14470,
    "X": 660,
    "Y": 582
  },
  {
    "Type": "MouseMove",
    "Time": 14544,
    "X": 769,
    "Y": 528
  },
  {
    "Type": "MouseMove",
    "Time": 14625,
    "X": 831,
    "Y": 540
  },
  {
    "Type": "MouseMove",
    "Time": 14699,
    "X": 877,
    "Y": 510
  },
  {
    "Type": "MouseMove",
    "Time": 14749,
    "X": 920,
    "Y": 455
  },
  {
    "Type": "MouseMove",
    "Time": 14768,
    "X": 933,
    "Y": 438
  },
  {
    "Type": "MouseMove",
    "Time": 14768,
    "X": 933,
    "Y": 438
  },
  {
    "Type": "MouseMove",
    "Time": 18543,
    "X": 933,
    "Y": 438,
    "Delta": null,
    "KeyCode": null
  },
  {
    "Type": "MouseMove",
    "Time": 18563,
    "X": 930,
    "Y": 438,
    "Delta": null,
    "KeyCode": null
  },
  {
    "Type": "MouseMove",
    "Time": 18583,
    "X": 927,
    "Y": 438,
    "Delta": null,
    "KeyCode": null
  },
  {
    "Type": "MouseMove",
    "Time": 18605,
    "X": 924,
    "Y": 438,
    "Delta": null,
    "KeyCode": null
  },
  {
    "Type": "MouseMove",
    "Time": 18627,
    "X": 921,
    "Y": 438,
    "Delta": null,
    "KeyCode": null
  },
  {
    "Type": "MouseMove",
    "Time": 18642,
    "X": 918,
    "Y": 438,
    "Delta": null,
    "KeyCode": null
  },
  {
    "Type": "MouseMove",
    "Time": 18657,
    "X": 918,
    "Y": 435,
    "Delta": null,
    "KeyCode": null
  },
  {
    "Type": "MouseMove",
    "Time": 18677,
    "X": 918,
    "Y": 432,
    "Delta": null,
    "KeyCode": null
  },
  {
    "Type": "MouseMove",
    "Time": 18699,
    "X": 915,
    "Y": 432,
    "Delta": null,
    "KeyCode": null
  },
  {
    "Type": "MouseMove",
    "Time": 18718,
    "X": 912,
    "Y": 432,
    "Delta": null,
    "KeyCode": null
  },
  {
    "Type": "MouseMove",
    "Time": 18738,
    "X": 909,
    "Y": 432,
    "Delta": null,
    "KeyCode": null
  },
  {
    "Type": "MouseMove",
    "Time": 18817,
    "X": 906,
    "Y": 426,
    "Delta": null,
    "KeyCode": null
  },
  {
    "Type": "MouseMove",
    "Time": 18837,
    "X": 906,
    "Y": 423,
    "Delta": null,
    "KeyCode": null
  },
  {
    "Type": "MouseMove",
    "Time": 18844,
    "X": 903,
    "Y": 420,
    "Delta": null,
    "KeyCode": null
  },
  {
    "Type": "MouseMove",
    "Time": 18856,
    "X": 900,
    "Y": 420,
    "Delta": null,
    "KeyCode": null
  },
  {
    "Type": "MouseMove",
    "Time": 19915,
    "X": 894,
    "Y": 417,
    "Delta": null,
    "KeyCode": null
  },
  {
    "Type": "MouseMove",
    "Time": 19938,
    "X": 888,
    "Y": 417,
    "Delta": null,
    "KeyCode": null
  },
  {
    "Type": "DragStart",
    "Time": 20002,
    "X": 888,
    "Y": 417,
    "Delta": null,
    "KeyCode": null
  },
  {
    "Type": "DragEnd",
    "Time": 20058,
    "X": 888,
    "Y": 417,
    "Delta": null,
    "KeyCode": null
  },
  {
    "Type": "MouseMove",
    "Time": 20122,
    "X": 891,
    "Y": 417,
    "Delta": null,
    "KeyCode": null
  },
  {
    "Type": "MouseMove",
    "Time": 20167,
    "X": 894,
    "Y": 420,
    "Delta": null,
    "KeyCode": null
  },
  {
    "Type": "MouseMove",
    "Time": 20190,
    "X": 894,
    "Y": 423,
    "Delta": null,
    "KeyCode": null
  },
  {
    "Type": "MouseMove",
    "Time": 20212,
    "X": 894,
    "Y": 426,
    "Delta": null,
    "KeyCode": null
  },
  {
    "Type": "MouseMove",
    "Time": 20345,
    "X": 897,
    "Y": 426,
    "Delta": null,
    "KeyCode": null
  },
  {
    "Type": "MouseMove",
    "Time": 20417,
    "X": 897,
    "Y": 429,
    "Delta": null,
    "KeyCode": null
  },
  {
    "Type": "MouseMove",
    "Time": 20561,
    "X": 897,
    "Y": 432,
    "Delta": null,
    "KeyCode": null
  },
  {
    "Type": "DragStart",
    "Time": 20692,
    "X": 897,
    "Y": 432,
    "Delta": null,
    "KeyCode": null
  },
  {
    "Type": "DragEnd",
    "Time": 20762,
    "X": 897,
    "Y": 432,
    "Delta": null,
    "KeyCode": null
  },
  {
    "Type": "DragStart",
    "Time": 21649,
    "X": 897,
    "Y": 432,
    "Delta": null,
    "KeyCode": null
  },
  {
    "Type": "DragEnd",
    "Time": 21726,
    "X": 897,
    "Y": 432,
    "Delta": null,
    "KeyCode": null
  },
  {
    "Type": "MouseMove",
    "Time": 21731,
    "X": 897,
    "Y": 429,
    "Delta": null,
    "KeyCode": null
  },
  {
    "Type": "MouseMove",
    "Time": 21758,
    "X": 897,
    "Y": 426,
    "Delta": null,
    "KeyCode": null
  },
  {
    "Type": "DragStart",
    "Time": 21855,
    "X": 897,
    "Y": 426,
    "Delta": null,
    "KeyCode": null
  },
  {
    "Type": "DragEnd",
    "Time": 21894,
    "X": 897,
    "Y": 426,
    "Delta": null,
    "KeyCode": null
  },
  {
    "Type": "MouseMove",
    "Time": 22061,
    "X": 897,
    "Y": 429,
    "Delta": null,
    "KeyCode": null
  },
  {
    "Type": "MouseMove",
    "Time": 22083,
    "X": 897,
    "Y": 432,
    "Delta": null,
    "KeyCode": null
  },
  {
    "Type": "MouseMove",
    "Time": 23037,
    "X": 900,
    "Y": 438,
    "Delta": null,
    "KeyCode": null
  },
  {
    "Type": "MouseMove",
    "Time": 23230,
    "X": 900,
    "Y": 441,
    "Delta": null,
    "KeyCode": null
  },
  {
    "Type": "MouseMove",
    "Time": 23277,
    "X": 900,
    "Y": 444,
    "Delta": null,
    "KeyCode": null
  },
  {
    "Type": "MouseMove",
    "Time": 25743,
    "X": 900,
    "Y": 441,
    "Delta": null,
    "KeyCode": null
  },
  {
    "Type": "MouseMove",
    "Time": 25791,
    "X": 900,
    "Y": 438,
    "Delta": null,
    "KeyCode": null
  },
  {
    "Type": "MouseMove",
    "Time": 25816,
    "X": 900,
    "Y": 435,
    "Delta": null,
    "KeyCode": null
  },
  {
    "Type": "MouseMove",
    "Time": 25847,
    "X": 900,
    "Y": 432,
    "Delta": null,
    "KeyCode": null
  },
  {
    "Type": "MouseMove",
    "Time": 25879,
    "X": 900,
    "Y": 429,
    "Delta": null,
    "KeyCode": null
  },
  {
    "Type": "DragStart",
    "Time": 26046,
    "X": 900,
    "Y": 429,
    "Delta": null,
    "KeyCode": null
  },
  {
    "Type": "DragEnd",
    "Time": 26110,
    "X": 900,
    "Y": 429,
    "Delta": null,
    "KeyCode": null
  },
  {
    "Type": "DragStart",
    "Time": 26273,
    "X": 900,
    "Y": 429,
    "Delta": null,
    "KeyCode": null
  },
  {
    "Type": "DragEnd",
    "Time": 26329,
    "X": 900,
    "Y": 429,
    "Delta": null,
    "KeyCode": null
  },
  {
    "Type": "MouseMove",
    "Time": 28861,
    "X": 903,
    "Y": 429,
    "Delta": null,
    "KeyCode": null
  },
  {
    "Type": "MouseMove",
    "Time": 29106,
    "X": 906,
    "Y": 429,
    "Delta": null,
    "KeyCode": null
  },
  {
    "Type": "DragStart",
    "Time": 29106,
    "X": 903,
    "Y": 429,
    "Delta": null,
    "KeyCode": null
  },
  {
    "Type": "MouseMove",
    "Time": 29106,
    "X": 903,
    "Y": 429,
    "Delta": null,
    "KeyCode": null
  },
  {
    "Type": "MouseMove",
    "Time": 29193,
    "X": 906,
    "Y": 429,
    "Delta": null,
    "KeyCode": null
  },
  {
    "Type": "DragEnd",
    "Time": 29194,
    "X": 906,
    "Y": 429,
    "Delta": null,
    "KeyCode": null
  },
  {
    "Type": "MouseMove",
    "Time": 29430,
    "X": 903,
    "Y": 432,
    "Delta": null,
    "KeyCode": null
  },
  {
    "Type": "DragStart",
    "Time": 29951,
    "X": 903,
    "Y": 432,
    "Delta": null,
    "KeyCode": null
  },
  {
    "Type": "DragEnd",
    "Time": 30018,
    "X": 903,
    "Y": 432,
    "Delta": null,
    "KeyCode": null
  },
  {
    "Type": "MouseMove",
    "Time": 32675,
    "X": 903,
    "Y": 429,
    "Delta": null,
    "KeyCode": null
  },
  {
    "Type": "DragStart",
    "Time": 32902,
    "X": 903,
    "Y": 429,
    "Delta": null,
    "KeyCode": null
  },
  {
    "Type": "DragEnd",
    "Time": 32975,
    "X": 903,
    "Y": 429,
    "Delta": null,
    "KeyCode": null
  },
  {
    "Type": "DragStart",
    "Time": 33208,
    "X": 903,
    "Y": 429,
    "Delta": null,
    "KeyCode": null
  },
  {
    "Type": "DragEnd",
    "Time": 33240,
    "X": 903,
    "Y": 429,
    "Delta": null,
    "KeyCode": null
  },
  {
    "Type": "DragStart",
    "Time": 35666,
    "X": 903,
    "Y": 429,
    "Delta": null,
    "KeyCode": null
  },
  {
    "Type": "DragEnd",
    "Time": 35733,
    "X": 903,
    "Y": 429,
    "Delta": null,
    "KeyCode": null
  },
  {
    "Type": "DragStart",
    "Time": 36608,
    "X": 903,
    "Y": 429,
    "Delta": null,
    "KeyCode": null
  },
  {
    "Type": "DragEnd",
    "Time": 36688,
    "X": 903,
    "Y": 429,
    "Delta": null,
    "KeyCode": null
  },
  {
    "Type": "MouseMove",
    "Time": 40639,
    "X": 903,
    "Y": 429
  },
  {
    "Type": "MouseMove",
    "Time": 40657,
    "X": 888,
    "Y": 430
  },
  {
    "Type": "MouseMove",
    "Time": 40709,
    "X": 863,
    "Y": 430
  },
  {
    "Type": "MouseMove",
    "Time": 40785,
    "X": 782,
    "Y": 411
  },
  {
    "Type": "MouseMove",
    "Time": 40868,
    "X": 763,
    "Y": 324
  },
  {
    "Type": "MouseMove",
    "Time": 40944,
    "X": 693,
    "Y": 336
  },
  {
    "Type": "MouseMove",
    "Time": 40996,
    "X": 663,
    "Y": 355
  },
  {
    "Type": "MouseMove",
    "Time": 41015,
    "X": 651,
    "Y": 360
  },
  {
    "Type": "MouseMove",
    "Time": 41015,
    "X": 651,
    "Y": 360
  },
  {
    "Type": "MouseMove",
    "Time": 44966,
    "X": 651,
    "Y": 360,
    "Delta": null,
    "KeyCode": null
  },
  {
    "Type": "MouseMove",
    "Time": 44987,
    "X": 666,
    "Y": 360,
    "Delta": null,
    "KeyCode": null
  },
  {
    "Type": "MouseMove",
    "Time": 45007,
    "X": 672,
    "Y": 360,
    "Delta": null,
    "KeyCode": null
  },
  {
    "Type": "MouseMove",
    "Time": 45028,
    "X": 684,
    "Y": 363,
    "Delta": null,
    "KeyCode": null
  },
  {
    "Type": "MouseMove",
    "Time": 45032,
    "X": 690,
    "Y": 363,
    "Delta": null,
    "KeyCode": null
  },
  {
    "Type": "MouseMove",
    "Time": 45040,
    "X": 693,
    "Y": 366,
    "Delta": null,
    "KeyCode": null
  },
  {
    "Type": "MouseMove",
    "Time": 45057,
    "X": 696,
    "Y": 366,
    "Delta": null,
    "KeyCode": null
  },
  {
    "Type": "MouseMove",
    "Time": 45058,
    "X": 702,
    "Y": 366,
    "Delta": null,
    "KeyCode": null
  },
  {
    "Type": "MouseMove",
    "Time": 45070,
    "X": 708,
    "Y": 366,
    "Delta": null,
    "KeyCode": null
  },
  {
    "Type": "MouseMove",
    "Time": 45089,
    "X": 723,
    "Y": 369,
    "Delta": null,
    "KeyCode": null
  },
  {
    "Type": "MouseMove",
    "Time": 45110,
    "X": 729,
    "Y": 372,
    "Delta": null,
    "KeyCode": null
  },
  {
    "Type": "MouseMove",
    "Time": 45112,
    "X": 732,
    "Y": 372,
    "Delta": null,
    "KeyCode": null
  },
  {
    "Type": "MouseMove",
    "Time": 45133,
    "X": 735,
    "Y": 372,
    "Delta": null,
    "KeyCode": null
  },
  {
    "Type": "MouseMove",
    "Time": 45146,
    "X": 738,
    "Y": 375,
    "Delta": null,
    "KeyCode": null
  },
  {
    "Type": "MouseMove",
    "Time": 45164,
    "X": 744,
    "Y": 375,
    "Delta": null,
    "KeyCode": null
  },
  {
    "Type": "MouseMove",
    "Time": 45185,
    "X": 756,
    "Y": 375,
    "Delta": null,
    "KeyCode": null
  },
  {
    "Type": "MouseMove",
    "Time": 45205,
    "X": 765,
    "Y": 375,
    "Delta": null,
    "KeyCode": null
  },
  {
    "Type": "MouseMove",
    "Time": 45226,
    "X": 774,
    "Y": 378,
    "Delta": null,
    "KeyCode": null
  },
  {
    "Type": "MouseMove",
    "Time": 45247,
    "X": 786,
    "Y": 378,
    "Delta": null,
    "KeyCode": null
  },
  {
    "Type": "MouseMove",
    "Time": 45269,
    "X": 795,
    "Y": 378,
    "Delta": null,
    "KeyCode": null
  },
  {
    "Type": "MouseMove",
    "Time": 45290,
    "X": 801,
    "Y": 378,
    "Delta": null,
    "KeyCode": null
  },
  {
    "Type": "MouseMove",
    "Time": 45291,
    "X": 804,
    "Y": 381,
    "Delta": null,
    "KeyCode": null
  },
  {
    "Type": "MouseMove",
    "Time": 45304,
    "X": 807,
    "Y": 381,
    "Delta": null,
    "KeyCode": null
  },
  {
    "Type": "MouseMove",
    "Time": 45318,
    "X": 810,
    "Y": 384,
    "Delta": null,
    "KeyCode": null
  },
  {
    "Type": "MouseMove",
    "Time": 45337,
    "X": 816,
    "Y": 384,
    "Delta": null,
    "KeyCode": null
  },
  {
    "Type": "MouseMove",
    "Time": 45356,
    "X": 822,
    "Y": 387,
    "Delta": null,
    "KeyCode": null
  },
  {
    "Type": "MouseMove",
    "Time": 45376,
    "X": 831,
    "Y": 390,
    "Delta": null,
    "KeyCode": null
  },
  {
    "Type": "MouseMove",
    "Time": 45398,
    "X": 837,
    "Y": 390,
    "Delta": null,
    "KeyCode": null
  },
  {
    "Type": "MouseMove",
    "Time": 45402,
    "X": 840,
    "Y": 390,
    "Delta": null,
    "KeyCode": null
  },
  {
    "Type": "MouseMove",
    "Time": 45431,
    "X": 840,
    "Y": 393,
    "Delta": null,
    "KeyCode": null
  },
  {
    "Type": "MouseMove",
    "Time": 45474,
    "X": 843,
    "Y": 396,
    "Delta": null,
    "KeyCode": null
  },
  {
    "Type": "MouseMove",
    "Time": 45494,
    "X": 846,
    "Y": 396,
    "Delta": null,
    "KeyCode": null
  },
  {
    "Type": "MouseMove",
    "Time": 45516,
    "X": 849,
    "Y": 399,
    "Delta": null,
    "KeyCode": null
  },
  {
    "Type": "MouseMove",
    "Time": 45536,
    "X": 852,
    "Y": 402,
    "Delta": null,
    "KeyCode": null
  },
  {
    "Type": "MouseMove",
    "Time": 45548,
    "X": 855,
    "Y": 405,
    "Delta": null,
    "KeyCode": null
  },
  {
    "Type": "MouseMove",
    "Time": 45577,
    "X": 864,
    "Y": 408,
    "Delta": null,
    "KeyCode": null
  },
  {
    "Type": "MouseMove",
    "Time": 45597,
    "X": 870,
    "Y": 411,
    "Delta": null,
    "KeyCode": null
  },
  {
    "Type": "MouseMove",
    "Time": 45615,
    "X": 873,
    "Y": 411,
    "Delta": null,
    "KeyCode": null
  },
  {
    "Type": "MouseMove",
    "Time": 45641,
    "X": 873,
    "Y": 414,
    "Delta": null,
    "KeyCode": null
  },
  {
    "Type": "MouseMove",
    "Time": 45682,
    "X": 876,
    "Y": 417,
    "Delta": null,
    "KeyCode": null
  },
  {
    "Type": "MouseMove",
    "Time": 45725,
    "X": 879,
    "Y": 420,
    "Delta": null,
    "KeyCode": null
  },
  {
    "Type": "MouseMove",
    "Time": 45748,
    "X": 879,
    "Y": 423,
    "Delta": null,
    "KeyCode": null
  },
  {
    "Type": "MouseMove",
    "Time": 45769,
    "X": 882,
    "Y": 423,
    "Delta": null,
    "KeyCode": null
  },
  {
    "Type": "MouseMove",
    "Time": 45775,
    "X": 882,
    "Y": 426,
    "Delta": null,
    "KeyCode": null
  },
  {
    "Type": "MouseMove",
    "Time": 45787,
    "X": 885,
    "Y": 426,
    "Delta": null,
    "KeyCode": null
  },
  {
    "Type": "MouseMove",
    "Time": 45846,
    "X": 888,
    "Y": 426,
    "Delta": null,
    "KeyCode": null
  },
  {
    "Type": "MouseMove",
    "Time": 45908,
    "X": 891,
    "Y": 426,
    "Delta": null,
    "KeyCode": null
  },
  {
    "Type": "MouseMove",
    "Time": 45951,
    "X": 894,
    "Y": 426,
    "Delta": null,
    "KeyCode": null
  },
  {
    "Type": "MouseMove",
    "Time": 46007,
    "X": 897,
    "Y": 426,
    "Delta": null,
    "KeyCode": null
  },
  {
    "Type": "MouseMove",
    "Time": 46023,
    "X": 900,
    "Y": 426,
    "Delta": null,
    "KeyCode": null
  },
  {
    "Type": "MouseMove",
    "Time": 46055,
    "X": 903,
    "Y": 426,
    "Delta": null,
    "KeyCode": null
  },
  {
    "Type": "DragStart",
    "Time": 46245,
    "X": 903,
    "Y": 426,
    "Delta": null,
    "KeyCode": null
  },
  {
    "Type": "DragEnd",
    "Time": 46304,
    "X": 903,
    "Y": 426,
    "Delta": null,
    "KeyCode": null
  },
  {
    "Type": "DragStart",
    "Time": 47269,
    "X": 903,
    "Y": 426,
    "Delta": null,
    "KeyCode": null
  },
  {
    "Type": "DragEnd",
    "Time": 47361,
    "X": 903,
    "Y": 426,
    "Delta": null,
    "KeyCode": null
  },
  {
    "Type": "MouseMove",
    "Time": 47861,
    "X": 900,
    "Y": 426,
    "Delta": null,
    "KeyCode": null
  },
  {
    "Type": "MouseMove",
    "Time": 47868,
    "X": 897,
    "Y": 426,
    "Delta": null,
    "KeyCode": null
  },
  {
    "Type": "MouseMove",
    "Time": 47896,
    "X": 894,
    "Y": 426,
    "Delta": null,
    "KeyCode": null
  },
  {
    "Type": "MouseMove",
    "Time": 48441,
    "X": 891,
    "Y": 426,
    "Delta": null,
    "KeyCode": null
  },
  {
    "Type": "MouseMove",
    "Time": 48631,
    "X": 888,
    "Y": 426,
    "Delta": null,
    "KeyCode": null
  },
  {
    "Type": "DragStart",
    "Time": 48858,
    "X": 888,
    "Y": 426,
    "Delta": null,
    "KeyCode": null
  },
  {
    "Type": "DragEnd",
    "Time": 48911,
    "X": 888,
    "Y": 426,
    "Delta": null,
    "KeyCode": null
  },
  {
    "Type": "MouseMove",
    "Time": 49678,
    "X": 888,
    "Y": 429,
    "Delta": null,
    "KeyCode": null
  },
  {
    "Type": "MouseMove",
    "Time": 49787,
    "X": 891,
    "Y": 429,
    "Delta": null,
    "KeyCode": null
  },
  {
    "Type": "MouseMove",
    "Time": 49793,
    "X": 891,
    "Y": 432,
    "Delta": null,
    "KeyCode": null
  },
  {
    "Type": "DragStart",
    "Time": 50339,
    "X": 891,
    "Y": 432,
    "Delta": null,
    "KeyCode": null
  },
  {
    "Type": "DragEnd",
    "Time": 50405,
    "X": 891,
    "Y": 432,
    "Delta": null,
    "KeyCode": null
  },
  {
    "Type": "MouseMove",
    "Time": 53188,
    "X": 891,
    "Y": 429,
    "Delta": null,
    "KeyCode": null
  },
  {
    "Type": "MouseMove",
    "Time": 53896,
    "X": 894,
    "Y": 429,
    "Delta": null,
    "KeyCode": null
  },
  {
    "Type": "MouseMove",
    "Time": 53823,
    "X": 897,
    "Y": 425
  },
  {
    "Type": "MouseMove",
    "Time": 53858,
    "X": 895,
    "Y": 424
  },
  {
    "Type": "MouseMove",
    "Time": 53893,
    "X": 894,
    "Y": 426
  },
  {
    "Type": "MouseMove",
    "Time": 53929,
    "X": 894,
    "Y": 426,
    "Delta": null,
    "KeyCode": null
  },
  {
    "Type": "MouseMove",
    "Time": 54201,
    "X": 891,
    "Y": 423
  },
  {
    "Type": "MouseMove",
    "Time": 54243,
    "X": 890,
    "Y": 425
  },
  {
    "Type": "MouseMove",
    "Time": 54285,
    "X": 893,
    "Y": 428
  },
  {
    "Type": "MouseMove",
    "Time": 54327,
    "X": 891,
    "Y": 426
  },
  {
    "Type": "MouseMove",
    "Time": 54372,
    "X": 891,
    "Y": 426,
    "Delta": null,
    "KeyCode": null
  },
  {
    "Type": "MouseMove",
    "Time": 54659,
    "X": 888,
    "Y": 426,
    "Delta": null,
    "KeyCode": null
  },
  {
    "Type": "MouseMove",
    "Time": 55051,
    "X": 885,
    "Y": 426,
    "Delta": null,
    "KeyCode": null
  },
  {
    "Type": "MouseMove",
    "Time": 55153,
    "X": 882,
    "Y": 426,
    "Delta": null,
    "KeyCode": null
  },
  {
    "Type": "MouseMove",
    "Time": 55247,
    "X": 879,
    "Y": 426,
    "Delta": null,
    "KeyCode": null
  },
  {
    "Type": "DragStart",
    "Time": 55450,
    "X": 879,
    "Y": 426,
    "Delta": null,
    "KeyCode": null
  },
  {
    "Type": "DragEnd",
    "Time": 55496,
    "X": 879,
    "Y": 426,
    "Delta": null,
    "KeyCode": null
  },
  {
    "Type": "MouseMove",
    "Time": 57414,
    "X": 882,
    "Y": 426,
    "Delta": null,
    "KeyCode": null
  },
  {
    "Type": "MouseMove",
    "Time": 57460,
    "X": 885,
    "Y": 426,
    "Delta": null,
    "KeyCode": null
  },
  {
    "Type": "MouseMove",
    "Time": 57515,
    "X": 888,
    "Y": 426,
    "Delta": null,
    "KeyCode": null
  },
  {
    "Type": "MouseMove",
    "Time": 57574,
    "X": 891,
    "Y": 426,
    "Delta": null,
    "KeyCode": null
  },
  {
    "Type": "MouseMove",
    "Time": 57848,
    "X": 894,
    "Y": 426,
    "Delta": null,
    "KeyCode": null
  },
  {
    "Type": "MouseMove",
    "Time": 57873,
    "X": 894,
    "Y": 429,
    "Delta": null,
    "KeyCode": null
  },
  {
    "Type": "MouseMove",
    "Time": 57905,
    "X": 897,
    "Y": 429,
    "Delta": null,
    "KeyCode": null
  },
  {
    "Type": "MouseMove",
    "Time": 57927,
    "X": 897,
    "Y": 432,
    "Delta": null,
    "KeyCode": null
  },
  {
    "Type": "MouseMove",
    "Time": 57938,
    "X": 900,
    "Y": 432,
    "Delta": null,
    "KeyCode": null
  },
  {
    "Type": "DragStart",
    "Time": 58116,
    "X": 900,
    "Y": 432,
    "Delta": null,
    "KeyCode": null
  },
  {
    "Type": "DragEnd",
    "Time": 58171,
    "X": 900,
    "Y": 432,
    "Delta": null,
    "KeyCode": null
  },
  {
    "Type": "MouseMove",
    "Time": 60271,
    "X": 900,
    "Y": 435
  },
  {
    "Type": "MouseMove",
    "Time": 60313,
    "X": 896,
    "Y": 434
  },
  {
    "Type": "MouseMove",
    "Time": 60355,
    "X": 897,
    "Y": 432
  },
  {
    "Type": "MouseMove",
    "Time": 60399,
    "X": 897,
    "Y": 432,
    "Delta": null,
    "KeyCode": null
  },
  {
    "Type": "MouseMove",
    "Time": 60308,
    "X": 897,
    "Y": 432
  },
  {
    "Type": "MouseMove",
    "Time": 60356,
    "X": 897,
    "Y": 435
  },
  {
    "Type": "MouseMove",
    "Time": 60404,
    "X": 894,
    "Y": 432
  },
  {
    "Type": "MouseMove",
    "Time": 60452,
    "X": 894,
    "Y": 432,
    "Delta": null,
    "KeyCode": null
  },
  {
    "Type": "MouseMove",
    "Time": 60950,
    "X": 894,
    "Y": 435,
    "Delta": null,
    "KeyCode": null
  },
  {
    "Type": "MouseMove",
    "Time": 61319,
    "X": 888,
    "Y": 434
  },
  {
    "Type": "MouseMove",
    "Time": 61355,
    "X": 890,
    "Y": 432
  },
  {
    "Type": "MouseMove",
    "Time": 61391,
    "X": 891,
    "Y": 435
  },
  {
    "Type": "MouseMove",
    "Time": 61429,
    "X": 891,
    "Y": 435,
    "Delta": null,
    "KeyCode": null
  },
  {
    "Type": "MouseMove",
    "Time": 62333,
    "X": 891,
    "Y": 432,
    "Delta": null,
    "KeyCode": null
  },
  {
    "Type": "MouseMove",
    "Time": 62473,
    "X": 891,
    "Y": 429,
    "Delta": null,
    "KeyCode": null
  },
  {
    "Type": "DragStart",
    "Time": 63111,
    "X": 891,
    "Y": 429,
    "Delta": null,
    "KeyCode": null
  },
  {
    "Type": "DragEnd",
    "Time": 63183,
    "X": 891,
    "Y": 429,
    "Delta": null,
    "KeyCode": null
  },
  {
    "Type": "MouseMove",
    "Time": 63763,
    "X": 894,
    "Y": 426,
    "Delta": null,
    "KeyCode": null
  },
  {
    "Type": "DragStart",
    "Time": 64017,
    "X": 894,
    "Y": 426,
    "Delta": null,
    "KeyCode": null
  },
  {
    "Type": "DragEnd",
    "Time": 64110,
    "X": 894,
    "Y": 426,
    "Delta": null,
    "KeyCode": null
  },
  {
    "Type": "MouseMove",
    "Time": 65030,
    "X": 894,
    "Y": 423,
    "Delta": null,
    "KeyCode": null
  },
  {
    "Type": "DragStart",
    "Time": 65635,
    "X": 894,
    "Y": 423,
    "Delta": null,
    "KeyCode": null
  },
  {
    "Type": "DragEnd",
    "Time": 65688,
    "X": 894,
    "Y": 423,
    "Delta": null,
    "KeyCode": null
  },
  {
    "Type": "MouseMove",
    "Time": 66001,
    "X": 894,
    "Y": 420,
    "Delta": null,
    "KeyCode": null
  },
  {
    "Type": "MouseMove",
    "Time": 66023,
    "X": 891,
    "Y": 417,
    "Delta": null,
    "KeyCode": null
  },
  {
    "Type": "MouseMove",
    "Time": 66933,
    "X": 888,
    "Y": 420,
    "Delta": null,
    "KeyCode": null
  },
  {
    "Type": "DragStart",
    "Time": 67205,
    "X": 888,
    "Y": 420,
    "Delta": null,
    "KeyCode": null
  },
  {
    "Type": "DragEnd",
    "Time": 67261,
    "X": 888,
    "Y": 420,
    "Delta": null,
    "KeyCode": null
  },
  {
    "Type": "MouseMove",
    "Time": 70410,
    "X": 882,
    "Y": 420
  },
  {
    "Type": "MouseMove",
    "Time": 70456,
    "X": 882,
    "Y": 418
  },
  {
    "Type": "MouseMove",
    "Time": 70502,
    "X": 884,
    "Y": 420
  },
  {
    "Type": "MouseMove",
    "Time": 70548,
    "X": 885,
    "Y": 420
  },
  {
    "Type": "MouseMove",
    "Time": 70596,
    "X": 885,
    "Y": 420,
    "Delta": null,
    "KeyCode": null
  },
  {
    "Type": "MouseMove",
    "Time": 70644,
    "X": 882,
    "Y": 420,
    "Delta": null,
    "KeyCode": null
  },
  {
    "Type": "MouseMove",
    "Time": 70510,
    "X": 877,
    "Y": 422
  },
  {
    "Type": "MouseMove",
    "Time": 70562,
    "X": 880,
    "Y": 424
  },
  {
    "Type": "MouseMove",
    "Time": 70614,
    "X": 879,
    "Y": 423
  },
  {
    "Type": "MouseMove",
    "Time": 70666,
    "X": 879,
    "Y": 423,
    "Delta": null,
    "KeyCode": null
  },
  {
    "Type": "MouseMove",
    "Time": 70519,
    "X": 875,
    "Y": 421
  },
  {
    "Type": "MouseMove",
    "Time": 70575,
    "X": 879,
    "Y": 424
  },
  {
    "Type": "MouseMove",
    "Time": 70631,
    "X": 876,
    "Y": 423
  },
  {
    "Type": "MouseMove",
    "Time": 70689,
    "X": 876,
    "Y": 423,
    "Delta": null,
    "KeyCode": null
  },
  {
    "Type": "MouseMove",
    "Time": 70628,
    "X": 876,
    "Y": 422
  },
  {
    "Type": "MouseMove",
    "Time": 70673,
    "X": 873,
    "Y": 421
  },
  {
    "Type": "MouseMove",
    "Time": 70718,
    "X": 876,
    "Y": 426
  },
  {
    "Type": "MouseMove",
    "Time": 70763,
    "X": 873,
    "Y": 423
  },
  {
    "Type": "MouseMove",
    "Time": 70809,
    "X": 873,
    "Y": 423,
    "Delta": null,
    "KeyCode": null
  },
  {
    "Type": "MouseMove",
    "Time": 70665,
    "X": 869,
    "Y": 421
  },
  {
    "Type": "MouseMove",
    "Time": 70701,
    "X": 871,
    "Y": 421
  },
  {
    "Type": "MouseMove",
    "Time": 70737,
    "X": 867,
    "Y": 421
  },
  {
    "Type": "MouseMove",
    "Time": 70773,
    "X": 870,
    "Y": 423
  },
  {
    "Type": "MouseMove",
    "Time": 70811,
    "X": 870,
    "Y": 423,
    "Delta": null,
    "KeyCode": null
  },
  {
    "Type": "MouseMove",
    "Time": 70837,
    "X": 861,
    "Y": 426,
    "Delta": null,
    "KeyCode": null
  },
  {
    "Type": "MouseMove",
    "Time": 70754,
    "X": 853,
    "Y": 428
  },
  {
    "Type": "MouseMove",
    "Time": 70780,
    "X": 855,
    "Y": 423
  },
  {
    "Type": "MouseMove",
    "Time": 70806,
    "X": 855,
    "Y": 424
  },
  {
    "Type": "MouseMove",
    "Time": 70832,
    "X": 852,
    "Y": 426
  },
  {
    "Type": "MouseMove",
    "Time": 70859,
    "X": 852,
    "Y": 426,
    "Delta": null,
    "KeyCode": null
  },
  {
    "Type": "MouseMove",
    "Time": 70724,
    "X": 839,
    "Y": 426
  },
  {
    "Type": "MouseMove",
    "Time": 70763,
    "X": 843,
    "Y": 430
  },
  {
    "Type": "MouseMove",
    "Time": 70802,
    "X": 840,
    "Y": 427
  },
  {
    "Type": "MouseMove",
    "Time": 70841,
    "X": 840,
    "Y": 429
  },
  {
    "Type": "MouseMove",
    "Time": 70881,
    "X": 840,
    "Y": 429,
    "Delta": null,
    "KeyCode": null
  },
  {
    "Type": "MouseMove",
    "Time": 70716,
    "X": 829,
    "Y": 429
  },
  {
    "Type": "MouseMove",
    "Time": 70778,
    "X": 832,
    "Y": 428
  },
  {
    "Type": "MouseMove",
    "Time": 70840,
    "X": 831,
    "Y": 429
  },
  {
    "Type": "MouseMove",
    "Time": 70903,
    "X": 831,
    "Y": 429,
    "Delta": null,
    "KeyCode": null
  },
  {
    "Type": "MouseMove",
    "Time": 70794,
    "X": 830,
    "Y": 432
  },
  {
    "Type": "MouseMove",
    "Time": 70822,
    "X": 829,
    "Y": 432
  },
  {
    "Type": "MouseMove",
    "Time": 70850,
    "X": 826,
    "Y": 433
  },
  {
    "Type": "MouseMove",
    "Time": 70878,
    "X": 828,
    "Y": 432
  },
  {
    "Type": "MouseMove",
    "Time": 70906,
    "X": 828,
    "Y": 432,
    "Delta": null,
    "KeyCode": null
  },
  {
    "Type": "MouseMove",
    "Time": 70809,
    "X": 823,
    "Y": 431
  },
  {
    "Type": "MouseMove",
    "Time": 70835,
    "X": 819,
    "Y": 429
  },
  {
    "Type": "MouseMove",
    "Time": 70861,
    "X": 825,
    "Y": 434
  },
  {
    "Type": "MouseMove",
    "Time": 70887,
    "X": 822,
    "Y": 432
  },
  {
    "Type": "MouseMove",
    "Time": 70916,
    "X": 822,
    "Y": 432,
    "Delta": null,
    "KeyCode": null
  },
  {
    "Type": "MouseMove",
    "Time": 70783,
    "X": 814,
    "Y": 434
  },
  {
    "Type": "MouseMove",
    "Time": 70822,
    "X": 811,
    "Y": 435
  },
  {
    "Type": "MouseMove",
    "Time": 70861,
    "X": 812,
    "Y": 431
  },
  {
    "Type": "MouseMove",
    "Time": 70900,
    "X": 813,
    "Y": 432
  },
  {
    "Type": "MouseMove",
    "Time": 70941,
    "X": 813,
    "Y": 432,
    "Delta": null,
    "KeyCode": null
  },
  {
    "Type": "MouseMove",
    "Time": 70823,
    "X": 806,
    "Y": 434
  },
  {
    "Type": "MouseMove",
    "Time": 70869,
    "X": 807,
    "Y": 432
  },
  {
    "Type": "MouseMove",
    "Time": 70915,
    "X": 804,
    "Y": 432
  },
  {
    "Type": "MouseMove",
    "Time": 70963,
    "X": 804,
    "Y": 432,
    "Delta": null,
    "KeyCode": null
  },
  {
    "Type": "MouseMove",
    "Time": 70782,
    "X": 798,
    "Y": 435
  },
  {
    "Type": "MouseMove",
    "Time": 72373,
    "X": 800,
    "Y": 429
  },
  {
    "Type": "MouseMove",
    "Time": 72433,
    "X": 801,
    "Y": 432
  },
  {
    "Type": "MouseMove",
    "Time": 72495,
    "X": 801,
    "Y": 432,
    "Delta": null,
    "KeyCode": null
  },
  {
    "Type": "MouseMove",
    "Time": 72323,
    "X": 798,
    "Y": 431
  },
  {
    "Type": "MouseMove",
    "Time": 72368,
    "X": 797,
    "Y": 432
  },
  {
    "Type": "MouseMove",
    "Time": 72413,
    "X": 801,
    "Y": 430
  },
  {
    "Type": "MouseMove",
    "Time": 72458,
    "X": 798,
    "Y": 432
  },
  {
    "Type": "MouseMove",
    "Time": 72503,
    "X": 798,
    "Y": 432,
    "Delta": null,
    "KeyCode": null
  },
  {
    "Type": "MouseMove",
    "Time": 72335,
    "X": 790,
    "Y": 433
  },
  {
    "Type": "MouseMove",
    "Time": 72393,
    "X": 793,
    "Y": 432
  },
  {
    "Type": "MouseMove",
    "Time": 72451,
    "X": 792,
    "Y": 435
  },
  {
    "Type": "MouseMove",
    "Time": 72511,
    "X": 792,
    "Y": 435,
    "Delta": null,
    "KeyCode": null
  },
  {
    "Type": "MouseMove",
    "Time": 72382,
    "X": 777,
    "Y": 433
  },
  {
    "Type": "MouseMove",
    "Time": 72421,
    "X": 779,
    "Y": 434
  },
  {
    "Type": "MouseMove",
    "Time": 72460,
    "X": 780,
    "Y": 435
  },
  {
    "Type": "MouseMove",
    "Time": 72499,
    "X": 780,
    "Y": 435
  },
  {
    "Type": "MouseMove",
    "Time": 72538,
    "X": 780,
    "Y": 435,
    "Delta": null,
    "KeyCode": null
  },
  {
    "Type": "MouseMove",
    "Time": 72543,
    "X": 774,
    "Y": 438,
    "Delta": null,
    "KeyCode": null
  },
  {
    "Type": "MouseMove",
    "Time": 72568,
    "X": 762,
    "Y": 441,
    "Delta": null,
    "KeyCode": null
  },
  {
    "Type": "MouseMove",
    "Time": 72406,
    "X": 761,
    "Y": 439
  },
  {
    "Type": "MouseMove",
    "Time": 72448,
    "X": 758,
    "Y": 441
  },
  {
    "Type": "MouseMove",
    "Time": 72490,
    "X": 757,
    "Y": 441
  },
  {
    "Type": "MouseMove",
    "Time": 72532,
    "X": 759,
    "Y": 441
  },
  {
    "Type": "MouseMove",
    "Time": 72575,
    "X": 759,
    "Y": 441,
    "Delta": null,
    "KeyCode": null
  },
  {
    "Type": "MouseMove",
    "Time": 72432,
    "X": 745,
    "Y": 441
  },
  {
    "Type": "MouseMove",
    "Time": 72474,
    "X": 743,
    "Y": 439
  },
  {
    "Type": "MouseMove",
    "Time": 72516,
    "X": 745,
    "Y": 438
  },
  {
    "Type": "MouseMove",
    "Time": 72558,
    "X": 744,
    "Y": 441
  },
  {
    "Type": "MouseMove",
    "Time": 72601,
    "X": 744,
    "Y": 441,
    "Delta": null,
    "KeyCode": null
  },
  {
    "Type": "MouseMove",
    "Time": 72470,
    "X": 741,
    "Y": 441
  },
  {
    "Type": "MouseMove",
    "Time": 72515,
    "X": 739,
    "Y": 447
  },
  {
    "Type": "MouseMove",
    "Time": 72560,
    "X": 741,
    "Y": 444
  },
  {
    "Type": "MouseMove",
    "Time": 72607,
    "X": 741,
    "Y": 444,
    "Delta": null,
    "KeyCode": null
  },
  {
    "Type": "MouseMove",
    "Time": 72525,
    "X": 729,
    "Y": 444
  },
  {
    "Type": "MouseMove",
    "Time": 72559,
    "X": 731,
    "Y": 442
  },
  {
    "Type": "MouseMove",
    "Time": 72593,
    "X": 729,
    "Y": 444
  },
  {
    "Type": "MouseMove",
    "Time": 72629,
    "X": 729,
    "Y": 444,
    "Delta": null,
    "KeyCode": null
  },
  {
    "Type": "MouseMove",
    "Time": 72516,
    "X": 709,
    "Y": 445
  },
  {
    "Type": "MouseMove",
    "Time": 72549,
    "X": 714,
    "Y": 446
  },
  {
    "Type": "MouseMove",
    "Time": 72582,
    "X": 714,
    "Y": 447
  },
  {
    "Type": "MouseMove",
    "Time": 72615,
    "X": 711,
    "Y": 444
  },
  {
    "Type": "MouseMove",
    "Time": 72651,
    "X": 711,
    "Y": 444,
    "Delta": null,
    "KeyCode": null
  },
  {
    "Type": "MouseMove",
    "Time": 72673,
    "X": 681,
    "Y": 450,
    "Delta": null,
    "KeyCode": null
  },
  {
    "Type": "MouseMove",
    "Time": 72698,
    "X": 645,
    "Y": 453,
    "Delta": null,
    "KeyCode": null
  },
  {
    "Type": "MouseMove",
    "Time": 72556,
    "X": 624,
    "Y": 457
  },
  {
    "Type": "MouseMove",
    "Time": 72610,
    "X": 619,
    "Y": 462
  },
  {
    "Type": "MouseMove",
    "Time": 72664,
    "X": 621,
    "Y": 459
  },
  {
    "Type": "MouseMove",
    "Time": 72720,
    "X": 621,
    "Y": 459,
    "Delta": null,
    "KeyCode": null
  },
  {
    "Type": "MouseMove",
    "Time": 72562,
    "X": 578,
    "Y": 460
  },
  {
    "Type": "MouseMove",
    "Time": 72622,
    "X": 582,
    "Y": 459
  },
  {
    "Type": "MouseMove",
    "Time": 72682,
    "X": 579,
    "Y": 462
  },
  {
    "Type": "MouseMove",
    "Time": 72743,
    "X": 579,
    "Y": 462,
    "Delta": null,
    "KeyCode": null
  },
  {
    "Type": "MouseMove",
    "Time": 72586,
    "X": 561,
    "Y": 467
  },
  {
    "Type": "MouseMove",
    "Time": 72645,
    "X": 561,
    "Y": 468
  },
  {
    "Type": "MouseMove",
    "Time": 72704,
    "X": 564,
    "Y": 465
  },
  {
    "Type": "MouseMove",
    "Time": 72765,
    "X": 564,
    "Y": 465,
    "Delta": null,
    "KeyCode": null
  },
  {
    "Type": "MouseMove",
    "Time": 72765,
    "X": 531,
    "Y": 471,
    "Delta": null,
    "KeyCode": null
  },
  {
    "Type": "MouseMove",
    "Time": 72649,
    "X": 489,
    "Y": 479
  },
  {
    "Type": "MouseMove",
    "Time": 72684,
    "X": 495,
    "Y": 476
  },
  {
    "Type": "MouseMove",
    "Time": 72719,
    "X": 493,
    "Y": 475
  },
  {
    "Type": "MouseMove",
    "Time": 72754,
    "X": 492,
    "Y": 477
  },
  {
    "Type": "MouseMove",
    "Time": 72789,
    "X": 492,
    "Y": 477,
    "Delta": null,
    "KeyCode": null
  },
  {
    "Type": "MouseMove",
    "Time": 72621,
    "X": 439,
    "Y": 484
  },
  {
    "Type": "MouseMove",
    "Time": 72669,
    "X": 441,
    "Y": 480
  },
  {
    "Type": "MouseMove",
    "Time": 72717,
    "X": 439,
    "Y": 483
  },
  {
    "Type": "MouseMove",
    "Time": 72765,
    "X": 441,
    "Y": 483
  },
  {
    "Type": "MouseMove",
    "Time": 72813,
    "X": 441,
    "Y": 483,
    "Delta": null,
    "KeyCode": null
  },
  {
    "Type": "MouseMove",
    "Time": 72703,
    "X": 399,
    "Y": 492
  },
  {
    "Type": "MouseMove",
    "Time": 72748,
    "X": 400,
    "Y": 486
  },
  {
    "Type": "MouseMove",
    "Time": 72793,
    "X": 402,
    "Y": 489
  },
  {
    "Type": "MouseMove",
    "Time": 72838,
    "X": 402,
    "Y": 489,
    "Delta": null,
    "KeyCode": null
  },
  {
    "Type": "MouseMove",
    "Time": 76748,
    "X": 402,
    "Y": 489
  },
  {
    "Type": "MouseMove",
    "Time": 76772,
    "X": 415,
    "Y": 470
  },
  {
    "Type": "MouseMove",
    "Time": 76836,
    "X": 470,
    "Y": 416
  },
  {
    "Type": "MouseMove",
    "Time": 76915,
    "X": 536,
    "Y": 358
  },
  {
    "Type": "MouseMove",
    "Time": 76979,
    "X": 617,
    "Y": 382
  },
  {
    "Type": "MouseMove",
    "Time": 77004,
    "X": 645,
    "Y": 393
  },
  {
    "Type": "MouseMove",
    "Time": 77004,
    "X": 645,
    "Y": 393
  },
  {
    "Type": "MouseMove",
    "Time": 80914,
    "X": 645,
    "Y": 393
  },
  {
    "Type": "MouseMove",
    "Time": 80967,
    "X": 645,
    "Y": 387
  },
  {
    "Type": "MouseMove",
    "Time": 81020,
    "X": 648,
    "Y": 390
  },
  {
    "Type": "MouseMove",
    "Time": 81073,
    "X": 648,
    "Y": 390,
    "Delta": null,
    "KeyCode": null
  },
  {
    "Type": "MouseMove",
    "Time": 80947,
    "X": 653,
    "Y": 388
  },
  {
    "Type": "MouseMove",
    "Time": 80990,
    "X": 651,
    "Y": 389
  },
  {
    "Type": "MouseMove",
    "Time": 81033,
    "X": 654,
    "Y": 390
  },
  {
    "Type": "MouseMove",
    "Time": 81077,
    "X": 654,
    "Y": 390,
    "Delta": null,
    "KeyCode": null
  },
  {
    "Type": "MouseMove",
    "Time": 80980,
    "X": 659,
    "Y": 395
  },
  {
    "Type": "MouseMove",
    "Time": 81006,
    "X": 662,
    "Y": 395
  },
  {
    "Type": "MouseMove",
    "Time": 81032,
    "X": 661,
    "Y": 390
  },
  {
    "Type": "MouseMove",
    "Time": 81058,
    "X": 660,
    "Y": 393
  },
  {
    "Type": "MouseMove",
    "Time": 81085,
    "X": 660,
    "Y": 393,
    "Delta": null,
    "KeyCode": null
  },
  {
    "Type": "MouseMove",
    "Time": 81094,
    "X": 666,
    "Y": 393,
    "Delta": null,
    "KeyCode": null
  },
  {
    "Type": "MouseMove",
    "Time": 80937,
    "X": 674,
    "Y": 395
  },
  {
    "Type": "MouseMove",
    "Time": 80978,
    "X": 671,
    "Y": 396
  },
  {
    "Type": "MouseMove",
    "Time": 81019,
    "X": 672,
    "Y": 396
  },
  {
    "Type": "MouseMove",
    "Time": 81060,
    "X": 672,
    "Y": 393
  },
  {
    "Type": "MouseMove",
    "Time": 81101,
    "X": 672,
    "Y": 393,
    "Delta": null,
    "KeyCode": null
  },
  {
    "Type": "MouseMove",
    "Time": 81114,
    "X": 678,
    "Y": 396,
    "Delta": null,
    "KeyCode": null
  },
  {
    "Type": "MouseMove",
    "Time": 81127,
    "X": 693,
    "Y": 396,
    "Delta": null,
    "KeyCode": null
  },
  {
    "Type": "MouseMove",
    "Time": 81043,
    "X": 706,
    "Y": 397
  },
  {
    "Type": "MouseMove",
    "Time": 81069,
    "X": 706,
    "Y": 398
  },
  {
    "Type": "MouseMove",
    "Time": 81095,
    "X": 711,
    "Y": 397
  },
  {
    "Type": "MouseMove",
    "Time": 81121,
    "X": 708,
    "Y": 399
  },
  {
    "Type": "MouseMove",
    "Time": 81148,
    "X": 708,
    "Y": 399,
    "Delta": null,
    "KeyCode": null
  },
  {
    "Type": "MouseMove",
    "Time": 81046,
    "X": 739,
    "Y": 400
  },
  {
    "Type": "MouseMove",
    "Time": 81087,
    "X": 737,
    "Y": 402
  },
  {
    "Type": "MouseMove",
    "Time": 81128,
    "X": 738,
    "Y": 399
  },
  {
    "Type": "MouseMove",
    "Time": 81169,
    "X": 738,
    "Y": 399,
    "Delta": null,
    "KeyCode": null
  },
  {
    "Type": "MouseMove",
    "Time": 81177,
    "X": 744,
    "Y": 402,
    "Delta": null,
    "KeyCode": null
  },
  {
    "Type": "MouseMove",
    "Time": 81191,
    "X": 753,
    "Y": 402,
    "Delta": null,
    "KeyCode": null
  },
  {
    "Type": "MouseMove",
    "Time": 81211,
    "X": 768,
    "Y": 402,
    "Delta": null,
    "KeyCode": null
  },
  {
    "Type": "MouseMove",
    "Time": 81016,
    "X": 775,
    "Y": 402
  },
  {
    "Type": "MouseMove",
    "Time": 81082,
    "X": 772,
    "Y": 402
  },
  {
    "Type": "MouseMove",
    "Time": 81148,
    "X": 774,
    "Y": 405
  },
  {
    "Type": "MouseMove",
    "Time": 81215,
    "X": 774,
    "Y": 405,
    "Delta": null,
    "KeyCode": null
  },
  {
    "Type": "MouseMove",
    "Time": 81084,
    "X": 782,
    "Y": 407
  },
  {
    "Type": "MouseMove",
    "Time": 81130,
    "X": 782,
    "Y": 406
  },
  {
    "Type": "MouseMove",
    "Time": 82643,
    "X": 780,
    "Y": 405
  },
  {
    "Type": "MouseMove",
    "Time": 82690,
    "X": 780,
    "Y": 405,
    "Delta": null,
    "KeyCode": null
  },
  {
    "Type": "MouseMove",
    "Time": 82514,
    "X": 783,
    "Y": 405
  },
  {
    "Type": "MouseMove",
    "Time": 82562,
    "X": 786,
    "Y": 411
  },
  {
    "Type": "MouseMove",
    "Time": 82610,
    "X": 785,
    "Y": 406
  },
  {
    "Type": "MouseMove",
    "Time": 82658,
    "X": 783,
    "Y": 408
  },
  {
    "Type": "MouseMove",
    "Time": 82706,
    "X": 783,
    "Y": 408,
    "Delta": null,
    "KeyCode": null
  },
  {
    "Type": "MouseMove",
    "Time": 82721,
    "X": 795,
    "Y": 408,
    "Delta": null,
    "KeyCode": null
  },
  {
    "Type": "MouseMove",
    "Time": 82742,
    "X": 807,
    "Y": 414,
    "Delta": null,
    "KeyCode": null
  },
  {
    "Type": "MouseMove",
    "Time": 82763,
    "X": 816,
    "Y": 414,
    "Delta": null,
    "KeyCode": null
  },
  {
    "Type": "MouseMove",
    "Time": 82609,
    "X": 819,
    "Y": 415
  },
  {
    "Type": "MouseMove",
    "Time": 82649,
    "X": 822,
    "Y": 415
  },
  {
    "Type": "MouseMove",
    "Time": 82689,
    "X": 819,
    "Y": 412
  },
  {
    "Type": "MouseMove",
    "Time": 82729,
    "X": 819,
    "Y": 414
  },
  {
    "Type": "MouseMove",
    "Time": 82770,
    "X": 819,
    "Y": 414,
    "Delta": null,
    "KeyCode": null
  },
  {
    "Type": "MouseMove",
    "Time": 82591,
    "X": 817,
    "Y": 418
  },
  {
    "Type": "MouseMove",
    "Time": 82639,
    "X": 817,
    "Y": 415
  },
  {
    "Type": "MouseMove",
    "Time": 82687,
    "X": 821,
    "Y": 419
  },
  {
    "Type": "MouseMove",
    "Time": 82735,
    "X": 819,
    "Y": 417
  },
  {
    "Type": "MouseMove",
    "Time": 82786,
    "X": 819,
    "Y": 417,
    "Delta": null,
    "KeyCode": null
  },
  {
    "Type": "MouseMove",
    "Time": 82632,
    "X": 824,
    "Y": 420
  },
  {
    "Type": "MouseMove",
    "Time": 82687,
    "X": 824,
    "Y": 419
  },
  {
    "Type": "MouseMove",
    "Time": 82742,
    "X": 822,
    "Y": 417
  },
  {
    "Type": "MouseMove",
    "Time": 82799,
    "X": 822,
    "Y": 417,
    "Delta": null,
    "KeyCode": null
  },
  {
    "Type": "MouseMove",
    "Time": 82819,
    "X": 825,
    "Y": 420,
    "Delta": null,
    "KeyCode": null
  },
  {
    "Type": "MouseMove",
    "Time": 82837,
    "X": 828,
    "Y": 423,
    "Delta": null,
    "KeyCode": null
  },
  {
    "Type": "MouseMove",
    "Time": 82842,
    "X": 831,
    "Y": 423,
    "Delta": null,
    "KeyCode": null
  },
  {
    "Type": "MouseMove",
    "Time": 82850,
    "X": 834,
    "Y": 423,
    "Delta": null,
    "KeyCode": null
  },
  {
    "Type": "MouseMove",
    "Time": 82865,
    "X": 834,
    "Y": 426,
    "Delta": null,
    "KeyCode": null
  },
  {
    "Type": "MouseMove",
    "Time": 82877,
    "X": 840,
    "Y": 426,
    "Delta": null,
    "KeyCode": null
  },
  {
    "Type": "MouseMove",
    "Time": 82896,
    "X": 846,
    "Y": 429,
    "Delta": null,
    "KeyCode": null
  },
  {
    "Type": "MouseMove",
    "Time": 82920,
    "X": 858,
    "Y": 432,
    "Delta": null,
    "KeyCode": null
  },
  {
    "Type": "MouseMove",
    "Time": 82924,
    "X": 864,
    "Y": 432,
    "Delta": null,
    "KeyCode": null
  },
  {
    "Type": "MouseMove",
    "Time": 82930,
    "X": 867,
    "Y": 432,
    "Delta": null,
    "KeyCode": null
  },
  {
    "Type": "MouseMove",
    "Time": 82942,
    "X": 870,
    "Y": 435,
    "Delta": null,
    "KeyCode": null
  },
  {
    "Type": "MouseMove",
    "Time": 82956,
    "X": 873,
    "Y": 435,
    "Delta": null,
    "KeyCode": null
  },
  {
    "Type": "MouseMove",
    "Time": 82974,
    "X": 876,
    "Y": 435,
    "Delta": null,
    "KeyCode": null
  },
  {
    "Type": "MouseMove",
    "Time": 82993,
    "X": 876,
    "Y": 438,
    "Delta": null,
    "KeyCode": null
  },
  {
    "Type": "MouseMove",
    "Time": 83003,
    "X": 879,
    "Y": 438,
    "Delta": null,
    "KeyCode": null
  },
  {
    "Type": "MouseMove",
    "Time": 83017,
    "X": 882,
    "Y": 438,
    "Delta": null,
    "KeyCode": null
  },
  {
    "Type": "MouseMove",
    "Time": 83037,
    "X": 885,
    "Y": 438,
    "Delta": null,
    "KeyCode": null
  },
  {
    "Type": "MouseMove",
    "Time": 83053,
    "X": 885,
    "Y": 441,
    "Delta": null,
    "KeyCode": null
  },
  {
    "Type": "MouseMove",
    "Time": 83222,
    "X": 888,
    "Y": 441,
    "Delta": null,
    "KeyCode": null
  },
  {
    "Type": "MouseMove",
    "Time": 83243,
    "X": 888,
    "Y": 438,
    "Delta": null,
    "KeyCode": null
  },
  {
    "Type": "MouseMove",
    "Time": 83246,
    "X": 891,
    "Y": 438,
    "Delta": null,
    "KeyCode": null
  },
  {
    "Type": "MouseMove",
    "Time": 83307,
    "X": 894,
    "Y": 435,
    "Delta": null,
    "KeyCode": null
  },
  {
    "Type": "MouseMove",
    "Time": 83350,
    "X": 897,
    "Y": 435,
    "Delta": null,
    "KeyCode": null
  },
  {
    "Type": "MouseMove",
    "Time": 83446,
    "X": 897,
    "Y": 432,
    "Delta": null,
    "KeyCode": null
  },
  {
    "Type": "MouseMove",
    "Time": 83547,
    "X": 900,
    "Y": 432,
    "Delta": null,
    "KeyCode": null
  },
  {
    "Type": "MouseMove",
    "Time": 83669,
    "X": 900,
    "Y": 429,
    "Delta": null,
    "KeyCode": null
  },
  {
    "Type": "MouseMove",
    "Time": 84023,
    "X": 903,
    "Y": 429,
    "Delta": null,
    "KeyCode": null
  },
  {
    "Type": "MouseMove",
    "Time": 84101,
    "X": 906,
    "Y": 429,
    "Delta": null,
    "KeyCode": null
  },
  {
    "Type": "DragStart",
    "Time": 84325,
    "X": 906,
    "Y": 429,
    "Delta": null,
    "KeyCode": null
  },
  {
    "Type": "DragEnd",
    "Time": 84439,
    "X": 906,
    "Y": 429,
    "Delta": null,
    "KeyCode": null
  },
  {
    "Type": "MouseMove",
    "Time": 85159,
    "X": 906,
    "Y": 432,
    "Delta": null,
    "KeyCode": null
  },
  {
    "Type": "MouseMove",
    "Time": 85248,
    "X": 903,
    "Y": 432,
    "Delta": null,
    "KeyCode": null
  },
  {
    "Type": "DragStart",
    "Time": 85363,
    "X": 903,
    "Y": 432,
    "Delta": null,
    "KeyCode": null
  },
  {
    "Type": "DragEnd",
    "Time": 85444,
    "X": 903,
    "Y": 432,
    "Delta": null,
    "KeyCode": null
  },
  {
    "Type": "MouseMove",
    "Time": 86812,
    "X": 903,
    "Y": 429,
    "Delta": null,
    "KeyCode": null
  },
  {
    "Type": "MouseMove",
    "Time": 86835,
    "X": 903,
    "Y": 426,
    "Delta": null,
    "KeyCode": null
  },
  {
    "Type": "DragStart",
    "Time": 87070,
    "X": 903,
    "Y": 426,
    "Delta": null,
    "KeyCode": null
  },
  {
    "Type": "DragEnd",
    "Time": 87160,
    "X": 903,
    "Y": 426,
    "Delta": null,
    "KeyCode": null
  },
  {
    "Type": "DragStart",
    "Time": 88945,
    "X": 903,
    "Y": 426,
    "Delta": null,
    "KeyCode": null
  },
  {
    "Type": "DragEnd",
    "Time": 89004,
    "X": 903,
    "Y": 426,
    "Delta": null,
    "KeyCode": null
  },
  {
    "Time": 90553,
    "Type": "MouseMove",
    "X": 903,
    "Y": 426
  },
  {
    "Time": 90606,
    "Type": "MouseMove",
    "X": 902,
    "Y": 424
  },
  {
    "Time": 90767,
    "Type": "MouseMove",
    "X": 907,
    "Y": 411
  },
  {
    "Time": 91036,
    "Type": "MouseMove",
    "X": 923,
    "Y": 392
  },
  {
    "Time": 91036,
    "Type": "MouseMove",
    "X": 923,
    "Y": 392
  },
  {
    "Time": 91055,
    "Type": "MouseMove",
    "X": 940,
    "Y": 377
  },
  {
    "Time": 91113,
    "Type": "MouseMove",
    "X": 931,
    "Y": 381
  },
  {
    "Time": 91209,
    "Type": "MouseMove",
    "X": 961,
    "Y": 376
  },
  {
    "Time": 91345,
    "Type": "MouseMove",
    "X": 963,
    "Y": 351
  },
  {
    "Time": 91519,
    "Type": "MouseMove",
    "X": 995,
    "Y": 345
  },
  {
    "Time": 91519,
    "Type": "MouseMove",
    "X": 995,
    "Y": 345
  },
  {
    "Time": 91538,
    "Type": "MouseMove",
    "X": 981,
    "Y": 341
  },
  {
    "Time": 91596,
    "Type": "MouseMove",
    "X": 979,
    "Y": 339
  },
  {
    "Time": 91692,
    "Type": "MouseMove",
    "X": 967,
    "Y": 339
  },
  {
    "Time": 91828,
    "Type": "MouseMove",
    "X": 940,
    "Y": 337
  },
  {
    "Time": 92002,
    "Type": "MouseMove",
    "X": 914,
    "Y": 338
  },
  {
    "Time": 92002,
    "Type": "MouseMove",
    "X": 914,
    "Y": 338
  },
  {
    "Time": 92175,
    "Type": "MouseMove",
    "X": 919,
    "Y": 370
  },
  {
    "Time": 92311,
    "Type": "MouseMove",
    "X": 943,
    "Y": 382
  },
  {
    "Time": 92407,
    "Type": "MouseMove",
    "X": 946,
    "Y": 387
  },
  {
    "Time": 92465,
    "Type": "MouseMove",
    "X": 965,
    "Y": 397
  },
  {
    "Time": 92485,
    "Type": "MouseMove",
    "X": 970,
    "Y": 398
  },
  {
    "Time": 92488,
    "Type": "MouseMove",
    "X": 970,
    "Y": 398
  },
  {
    "Time": 92582,
    "Type": "MouseMove",
    "X": 954,
    "Y": 395
  },
  {
    "Time": 92809,
    "Type": "MouseMove",
    "X": 929,
    "Y": 396
  },
  {
    "Time": 93037,
    "Type": "MouseMove",
    "X": 910,
    "Y": 415
  },
  {
    "Time": 93132,
    "Type": "MouseMove",
    "X": 903,
    "Y": 426
  },
  {
    "Type": "DragStart",
    "Time": 94681,
    "X": 903,
    "Y": 426,
    "Delta": null,
    "KeyCode": null
  },
  {
    "Type": "DragEnd",
    "Time": 94799,
    "X": 903,
    "Y": 426,
    "Delta": null,
    "KeyCode": null
  },
  {
    "Type": "DragStart",
    "Time": 95031,
    "X": 903,
    "Y": 426,
    "Delta": null,
    "KeyCode": null
  },
  {
    "Type": "DragEnd",
    "Time": 95120,
    "X": 903,
    "Y": 426,
    "Delta": null,
    "KeyCode": null
  },
  {
    "Type": "MouseMove",
    "Time": 99192,
    "X": 903,
    "Y": 426
  },
  {
    "Type": "MouseMove",
    "Time": 99299,
    "X": 776,
    "Y": 473
  },
  {
    "Type": "MouseMove",
    "Time": 99382,
    "X": 690,
    "Y": 525
  },
  {
    "Type": "MouseMove",
    "Time": 99442,
    "X": 621,
    "Y": 570
  },
  {
    "Type": "MouseMove",
    "Time": 99478,
    "X": 592,
    "Y": 589
  },
  {
    "Type": "MouseMove",
    "Time": 99490,
    "X": 573,
    "Y": 597
  },
  {
    "Type": "MouseMove",
    "Time": 99490,
    "X": 573,
    "Y": 597
  },
  {
    "Type": "MouseMove",
    "Time": 103562,
    "X": 573,
    "Y": 597,
    "Delta": null,
    "KeyCode": null
  },
  {
    "Type": "MouseMove",
    "Time": 103587,
    "X": 582,
    "Y": 591,
    "Delta": null,
    "KeyCode": null
  },
  {
    "Type": "MouseMove",
    "Time": 103608,
    "X": 594,
    "Y": 582,
    "Delta": null,
    "KeyCode": null
  },
  {
    "Type": "MouseMove",
    "Time": 103631,
    "X": 612,
    "Y": 573,
    "Delta": null,
    "KeyCode": null
  },
  {
    "Type": "MouseMove",
    "Time": 103652,
    "X": 630,
    "Y": 561,
    "Delta": null,
    "KeyCode": null
  },
  {
    "Type": "MouseMove",
    "Time": 103655,
    "X": 639,
    "Y": 558,
    "Delta": null,
    "KeyCode": null
  },
  {
    "Type": "MouseMove",
    "Time": 103672,
    "X": 660,
    "Y": 546,
    "Delta": null,
    "KeyCode": null
  },
  {
    "Type": "MouseMove",
    "Time": 103685,
    "X": 669,
    "Y": 540,
    "Delta": null,
    "KeyCode": null
  },
  {
    "Type": "MouseMove",
    "Time": 103709,
    "X": 696,
    "Y": 528,
    "Delta": null,
    "KeyCode": null
  },
  {
    "Type": "MouseMove",
    "Time": 103734,
    "X": 726,
    "Y": 510,
    "Delta": null,
    "KeyCode": null
  },
  {
    "Type": "MouseMove",
    "Time": 103756,
    "X": 753,
    "Y": 495,
    "Delta": null,
    "KeyCode": null
  },
  {
    "Type": "MouseMove",
    "Time": 103775,
    "X": 774,
    "Y": 483,
    "Delta": null,
    "KeyCode": null
  },
  {
    "Type": "MouseMove",
    "Time": 103796,
    "X": 783,
    "Y": 477,
    "Delta": null,
    "KeyCode": null
  },
  {
    "Type": "MouseMove",
    "Time": 103799,
    "X": 789,
    "Y": 474,
    "Delta": null,
    "KeyCode": null
  },
  {
    "Type": "MouseMove",
    "Time": 103810,
    "X": 792,
    "Y": 471,
    "Delta": null,
    "KeyCode": null
  },
  {
    "Type": "MouseMove",
    "Time": 103824,
    "X": 798,
    "Y": 468,
    "Delta": null,
    "KeyCode": null
  },
  {
    "Type": "MouseMove",
    "Time": 103847,
    "X": 804,
    "Y": 462,
    "Delta": null,
    "KeyCode": null
  },
  {
    "Type": "MouseMove",
    "Time": 103870,
    "X": 807,
    "Y": 462,
    "Delta": null,
    "KeyCode": null
  },
  {
    "Type": "MouseMove",
    "Time": 103891,
    "X": 810,
    "Y": 462,
    "Delta": null,
    "KeyCode": null
  },
  {
    "Type": "MouseMove",
    "Time": 103895,
    "X": 810,
    "Y": 459,
    "Delta": null,
    "KeyCode": null
  },
  {
    "Type": "MouseMove",
    "Time": 103928,
    "X": 813,
    "Y": 456,
    "Delta": null,
    "KeyCode": null
  },
  {
    "Type": "MouseMove",
    "Time": 103941,
    "X": 816,
    "Y": 453,
    "Delta": null,
    "KeyCode": null
  },
  {
    "Type": "MouseMove",
    "Time": 103963,
    "X": 822,
    "Y": 447,
    "Delta": null,
    "KeyCode": null
  },
  {
    "Type": "MouseMove",
    "Time": 103986,
    "X": 831,
    "Y": 444,
    "Delta": null,
    "KeyCode": null
  },
  {
    "Type": "MouseMove",
    "Time": 104007,
    "X": 837,
    "Y": 438,
    "Delta": null,
    "KeyCode": null
  },
  {
    "Type": "MouseMove",
    "Time": 104009,
    "X": 840,
    "Y": 438,
    "Delta": null,
    "KeyCode": null
  },
  {
    "Type": "MouseMove",
    "Time": 104034,
    "X": 843,
    "Y": 435,
    "Delta": null,
    "KeyCode": null
  },
  {
    "Type": "MouseMove",
    "Time": 104055,
    "X": 846,
    "Y": 435,
    "Delta": null,
    "KeyCode": null
  },
  {
    "Type": "MouseMove",
    "Time": 104076,
    "X": 846,
    "Y": 432,
    "Delta": null,
    "KeyCode": null
  },
  {
    "Type": "MouseMove",
    "Time": 104095,
    "X": 849,
    "Y": 432,
    "Delta": null,
    "KeyCode": null
  },
  {
    "Type": "MouseMove",
    "Time": 104116,
    "X": 852,
    "Y": 432,
    "Delta": null,
    "KeyCode": null
  },
  {
    "Type": "MouseMove",
    "Time": 104121,
    "X": 855,
    "Y": 432,
    "Delta": null,
    "KeyCode": null
  },
  {
    "Type": "MouseMove",
    "Time": 104162,
    "X": 858,
    "Y": 429,
    "Delta": null,
    "KeyCode": null
  },
  {
    "Type": "MouseMove",
    "Time": 104184,
    "X": 861,
    "Y": 429,
    "Delta": null,
    "KeyCode": null
  },
  {
    "Type": "MouseMove",
    "Time": 104206,
    "X": 864,
    "Y": 429,
    "Delta": null,
    "KeyCode": null
  },
  {
    "Type": "MouseMove",
    "Time": 104229,
    "X": 867,
    "Y": 429,
    "Delta": null,
    "KeyCode": null
  },
  {
    "Type": "MouseMove",
    "Time": 104256,
    "X": 870,
    "Y": 426,
    "Delta": null,
    "KeyCode": null
  },
  {
    "Type": "MouseMove",
    "Time": 104278,
    "X": 873,
    "Y": 426,
    "Delta": null,
    "KeyCode": null
  },
  {
    "Type": "MouseMove",
    "Time": 104283,
    "X": 876,
    "Y": 426,
    "Delta": null,
    "KeyCode": null
  },
  {
    "Type": "MouseMove",
    "Time": 104342,
    "X": 879,
    "Y": 426,
    "Delta": null,
    "KeyCode": null
  },
  {
    "Type": "MouseMove",
    "Time": 104408,
    "X": 882,
    "Y": 426,
    "Delta": null,
    "KeyCode": null
  },
  {
    "Type": "MouseMove",
    "Time": 104491,
    "X": 885,
    "Y": 426,
    "Delta": null,
    "KeyCode": null
  },
  {
    "Type": "MouseMove",
    "Time": 104511,
    "X": 888,
    "Y": 426,
    "Delta": null,
    "KeyCode": null
  },
  {
    "Type": "MouseMove",
    "Time": 104557,
    "X": 891,
    "Y": 426,
    "Delta": null,
    "KeyCode": null
  },
  {
    "Type": "MouseMove",
    "Time": 104577,
    "X": 894,
    "Y": 426,
    "Delta": null,
    "KeyCode": null
  },
  {
    "Type": "DragStart",
    "Time": 104787,
    "X": 894,
    "Y": 426,
    "Delta": null,
    "KeyCode": null
  },
  {
    "Type": "DragEnd",
    "Time": 104841,
    "X": 894,
    "Y": 426,
    "Delta": null,
    "KeyCode": null
  },
  {
    "Type": "MouseMove",
    "Time": 105395,
    "X": 897,
    "Y": 426,
    "Delta": null,
    "KeyCode": null
  },
  {
    "Type": "MouseMove",
    "Time": 105420,
    "X": 897,
    "Y": 429,
    "Delta": null,
    "KeyCode": null
  },
  {
    "Type": "DragStart",
    "Time": 105467,
    "X": 897,
    "Y": 429,
    "Delta": null,
    "KeyCode": null
  },
  {
    "Type": "DragEnd",
    "Time": 105613,
    "X": 897,
    "Y": 429,
    "Delta": null,
    "KeyCode": null
  },
  {
    "Type": "MouseMove",
    "Time": 107166,
    "X": 900,
    "Y": 429,
    "Delta": null,
    "KeyCode": null
  },
  {
    "Type": "MouseMove",
    "Time": 107167,
    "X": 900,
    "Y": 426,
    "Delta": null,
    "KeyCode": null
  },
  {
    "Type": "MouseMove",
    "Time": 107739,
    "X": 900,
    "Y": 423,
    "Delta": null,
    "KeyCode": null
  },
  {
    "Type": "DragStart",
    "Time": 108044,
    "X": 900,
    "Y": 423,
    "Delta": null,
    "KeyCode": null
  },
  {
    "Type": "DragEnd",
    "Time": 108126,
    "X": 900,
    "Y": 423,
    "Delta": null,
    "KeyCode": null
  },
  {
    "Type": "MouseMove",
    "Time": 108483,
    "X": 900,
    "Y": 426,
    "Delta": null,
    "KeyCode": null
  },
  {
    "Type": "DragStart",
    "Time": 109320,
    "X": 900,
    "Y": 426,
    "Delta": null,
    "KeyCode": null
  },
  {
    "Type": "DragEnd",
    "Time": 109419,
    "X": 900,
    "Y": 426,
    "Delta": null,
    "KeyCode": null
  },
  {
    "Type": "MouseMove",
    "Time": 109532,
    "X": 894,
    "Y": 429,
    "Delta": null,
    "KeyCode": null
  },
  {
    "Type": "MouseMove",
    "Time": 109555,
    "X": 888,
    "Y": 432,
    "Delta": null,
    "KeyCode": null
  },
  {
    "Type": "MouseMove",
    "Time": 109578,
    "X": 885,
    "Y": 423,
    "Delta": null,
    "KeyCode": null
  },
  {
    "Type": "MouseMove",
    "Time": 109583,
    "X": 894,
    "Y": 414,
    "Delta": null,
    "KeyCode": null
  },
  {
    "Type": "MouseMove",
    "Time": 109591,
    "X": 903,
    "Y": 408,
    "Delta": null,
    "KeyCode": null
  },
  {
    "Type": "MouseMove",
    "Time": 109614,
    "X": 918,
    "Y": 399,
    "Delta": null,
    "KeyCode": null
  },
  {
    "Type": "MouseMove",
    "Time": 111387,
    "X": 921,
    "Y": 396,
    "Delta": null,
    "KeyCode": null
  },
  {
    "Type": "MouseMove",
    "Time": 111410,
    "X": 927,
    "Y": 390,
    "Delta": null,
    "KeyCode": null
  },
  {
    "Type": "MouseMove",
    "Time": 111431,
    "X": 930,
    "Y": 384,
    "Delta": null,
    "KeyCode": null
  },
  {
    "Type": "MouseMove",
    "Time": 111477,
    "X": 933,
    "Y": 381,
    "Delta": null,
    "KeyCode": null
  },
  {
    "Type": "MouseMove",
    "Time": 111589,
    "X": 930,
    "Y": 381,
    "Delta": null,
    "KeyCode": null
  },
  {
    "Type": "MouseMove",
    "Time": 111618,
    "X": 927,
    "Y": 387,
    "Delta": null,
    "KeyCode": null
  },
  {
    "Type": "MouseMove",
    "Time": 111621,
    "X": 924,
    "Y": 387,
    "Delta": null,
    "KeyCode": null
  },
  {
    "Type": "MouseMove",
    "Time": 111649,
    "X": 921,
    "Y": 390,
    "Delta": null,
    "KeyCode": null
  },
  {
    "Type": "MouseMove",
    "Time": 111653,
    "X": 918,
    "Y": 390,
    "Delta": null,
    "KeyCode": null
  },
  {
    "Type": "MouseMove",
    "Time": 111701,
    "X": 918,
    "Y": 393,
    "Delta": null,
    "KeyCode": null
  },
  {
    "Type": "MouseMove",
    "Time": 111722,
    "X": 915,
    "Y": 396,
    "Delta": null,
    "KeyCode": null
  },
  {
    "Type": "MouseMove",
    "Time": 111743,
    "X": 912,
    "Y": 396,
    "Delta": null,
    "KeyCode": null
  },
  {
    "Type": "MouseMove",
    "Time": 111825,
    "X": 918,
    "Y": 396,
    "Delta": null,
    "KeyCode": null
  },
  {
    "Type": "MouseMove",
    "Time": 111848,
    "X": 930,
    "Y": 396,
    "Delta": null,
    "KeyCode": null
  },
  {
    "Type": "MouseMove",
    "Time": 111869,
    "X": 936,
    "Y": 396,
    "Delta": null,
    "KeyCode": null
  },
  {
    "Type": "MouseMove",
    "Time": 111889,
    "X": 939,
    "Y": 396,
    "Delta": null,
    "KeyCode": null
  },
  {
    "Type": "DragStart",
    "Time": 112140,
    "X": 939,
    "Y": 396,
    "Delta": null,
    "KeyCode": null
  },
  {
    "Type": "DragEnd",
    "Time": 112244,
    "X": 939,
    "Y": 396,
    "Delta": null,
    "KeyCode": null
  },
  {
    "Type": "MouseMove",
    "Time": 112416,
    "X": 936,
    "Y": 399,
    "Delta": null,
    "KeyCode": null
  },
  {
    "Type": "MouseMove",
    "Time": 112419,
    "X": 936,
    "Y": 402,
    "Delta": null,
    "KeyCode": null
  },
  {
    "Type": "MouseMove",
    "Time": 112444,
    "X": 930,
    "Y": 408,
    "Delta": null,
    "KeyCode": null
  },
  {
    "Type": "MouseMove",
    "Time": 112492,
    "X": 924,
    "Y": 411,
    "Delta": null,
    "KeyCode": null
  },
  {
    "Type": "MouseMove",
    "Time": 112515,
    "X": 921,
    "Y": 414,
    "Delta": null,
    "KeyCode": null
  },
  {
    "Type": "MouseMove",
    "Time": 112516,
    "X": 918,
    "Y": 414,
    "Delta": null,
    "KeyCode": null
  },
  {
    "Type": "MouseMove",
    "Time": 112538,
    "X": 912,
    "Y": 417,
    "Delta": null,
    "KeyCode": null
  },
  {
    "Type": "MouseMove",
    "Time": 112562,
    "X": 906,
    "Y": 423,
    "Delta": null,
    "KeyCode": null
  },
  {
    "Type": "MouseMove",
    "Time": 112584,
    "X": 903,
    "Y": 423,
    "Delta": null,
    "KeyCode": null
  },
  {
    "Type": "MouseMove",
    "Time": 112725,
    "X": 903,
    "Y": 426,
    "Delta": null,
    "KeyCode": null
  },
  {
    "Type": "DragStart",
    "Time": 112725,
    "X": 903,
    "Y": 423,
    "Delta": null,
    "KeyCode": null
  },
  {
    "Type": "MouseMove",
    "Time": 112725,
    "X": 903,
    "Y": 423,
    "Delta": null,
    "KeyCode": null
  },
  {
    "Type": "MouseMove",
    "Time": 112795,
    "X": 903,
    "Y": 426,
    "Delta": null,
    "KeyCode": null
  },
  {
    "Type": "DragEnd",
    "Time": 112796,
    "X": 903,
    "Y": 426,
    "Delta": null,
    "KeyCode": null
  },
  {
    "Type": "DragStart",
    "Time": 113307,
    "X": 903,
    "Y": 426,
    "Delta": null,
    "KeyCode": null
  },
  {
    "Type": "DragEnd",
    "Time": 113393,
    "X": 903,
    "Y": 426,
    "Delta": null,
    "KeyCode": null
  },
  {
    "Type": "MouseMove",
    "Time": 115862,
    "X": 900,
    "Y": 426,
    "Delta": null,
    "KeyCode": null
  },
  {
    "Type": "MouseMove",
    "Time": 115906,
    "X": 897,
    "Y": 426,
    "Delta": null,
    "KeyCode": null
  },
  {
    "Type": "MouseMove",
    "Time": 116910,
    "X": 894,
    "Y": 426,
    "Delta": null,
    "KeyCode": null
  },
  {
    "Type": "MouseMove",
    "Time": 116945,
    "X": 894,
    "Y": 429,
    "Delta": null,
    "KeyCode": null
  },
  {
    "Type": "DragStart",
    "Time": 117296,
    "X": 894,
    "Y": 429,
    "Delta": null,
    "KeyCode": null
  },
  {
    "Type": "DragEnd",
    "Time": 117342,
    "X": 894,
    "Y": 429,
    "Delta": null,
    "KeyCode": null
  },
  {
    "Type": "DragStart",
    "Time": 117605,
    "X": 894,
    "Y": 429,
    "Delta": null,
    "KeyCode": null
  },
  {
    "Type": "DragEnd",
    "Time": 117678,
    "X": 894,
    "Y": 429,
    "Delta": null,
    "KeyCode": null
  },
  {
    "Type": "MouseMove",
    "Time": 118577,
    "X": 894,
    "Y": 426,
    "Delta": null,
    "KeyCode": null
  },
  {
    "Type": "MouseMove",
    "Time": 118946,
    "X": 897,
    "Y": 429,
    "Delta": null,
    "KeyCode": null
  },
  {
    "Type": "MouseMove",
    "Time": 118968,
    "X": 897,
    "Y": 432,
    "Delta": null,
    "KeyCode": null
  },
  {
    "Type": "MouseMove",
    "Time": 119703,
    "X": 900,
    "Y": 432,
    "Delta": null,
    "KeyCode": null
  },
  {
    "Type": "MouseMove",
    "Time": 119757,
    "X": 900,
    "Y": 429,
    "Delta": null,
    "KeyCode": null
  },
  {
    "Type": "MouseMove",
    "Time": 119777,
    "X": 903,
    "Y": 429,
    "Delta": null,
    "KeyCode": null
  },
  {
    "Type": "MouseMove",
    "Time": 119778,
    "X": 906,
    "Y": 429,
    "Delta": null,
    "KeyCode": null
  },
  {
    "Type": "MouseMove",
    "Time": 119801,
    "X": 906,
    "Y": 426,
    "Delta": null,
    "KeyCode": null
  },
  {
    "Type": "MouseMove",
    "Time": 120450,
    "X": 903,
    "Y": 426,
    "Delta": null,
    "KeyCode": null
  },
  {
    "Type": "MouseMove",
    "Time": 120531,
    "X": 900,
    "Y": 426,
    "Delta": null,
    "KeyCode": null
  },
  {
    "Type": "DragStart",
    "Time": 120701,
    "X": 900,
    "Y": 426,
    "Delta": null,
    "KeyCode": null
  },
  {
    "Type": "DragEnd",
    "Time": 120793,
    "X": 900,
    "Y": 426,
    "Delta": null,
    "KeyCode": null
  },
  {
    "Type": "DragStart",
    "Time": 121081,
    "X": 900,
    "Y": 426,
    "Delta": null,
    "KeyCode": null
  },
  {
    "Type": "DragEnd",
    "Time": 121160,
    "X": 900,
    "Y": 426,
    "Delta": null,
    "KeyCode": null
  },
  {
    "Type": "MouseMove",
    "Time": 121473,
    "X": 897,
    "Y": 426,
    "Delta": null,
    "KeyCode": null
  },
  {
    "Type": "MouseMove",
    "Time": 121502,
    "X": 891,
    "Y": 429,
    "Delta": null,
    "KeyCode": null
  },
  {
    "Type": "MouseMove",
    "Time": 121505,
    "X": 888,
    "Y": 432,
    "Delta": null,
    "KeyCode": null
  },
  {
    "Type": "MouseMove",
    "Time": 121531,
    "X": 885,
    "Y": 432,
    "Delta": null,
    "KeyCode": null
  },
  {
    "Type": "MouseMove",
    "Time": 121563,
    "X": 882,
    "Y": 432,
    "Delta": null,
    "KeyCode": null
  },
  {
    "Type": "MouseMove",
    "Time": 121584,
    "X": 867,
    "Y": 432,
    "Delta": null,
    "KeyCode": null
  },
  {
    "Type": "MouseMove",
    "Time": 121585,
    "X": 858,
    "Y": 429,
    "Delta": null,
    "KeyCode": null
  },
  {
    "Type": "MouseMove",
    "Time": 122722,
    "X": 849,
    "Y": 426,
    "Delta": null,
    "KeyCode": null
  },
  {
    "Type": "MouseMove",
    "Time": 122730,
    "X": 846,
    "Y": 426,
    "Delta": null,
    "KeyCode": null
  },
  {
    "Type": "MouseMove",
    "Time": 123140,
    "X": 846,
    "Y": 432,
    "Delta": null,
    "KeyCode": null
  },
  {
    "Type": "MouseMove",
    "Time": 123142,
    "X": 846,
    "Y": 435,
    "Delta": null,
    "KeyCode": null
  },
  {
    "Type": "MouseMove",
    "Time": 123150,
    "X": 849,
    "Y": 438,
    "Delta": null,
    "KeyCode": null
  },
  {
    "Type": "MouseMove",
    "Time": 123158,
    "X": 849,
    "Y": 441,
    "Delta": null,
    "KeyCode": null
  },
  {
    "Type": "MouseMove",
    "Time": 123183,
    "X": 852,
    "Y": 447,
    "Delta": null,
    "KeyCode": null
  },
  {
    "Type": "MouseMove",
    "Time": 123205,
    "X": 852,
    "Y": 453,
    "Delta": null,
    "KeyCode": null
  },
  {
    "Type": "MouseMove",
    "Time": 123229,
    "X": 852,
    "Y": 456,
    "Delta": null,
    "KeyCode": null
  },
  {
    "Type": "MouseMove",
    "Time": 124751,
    "X": 855,
    "Y": 459,
    "Delta": null,
    "KeyCode": null
  },
  {
    "Type": "MouseMove",
    "Time": 124929,
    "X": 858,
    "Y": 453,
    "Delta": null,
    "KeyCode": null
  },
  {
    "Type": "MouseMove",
    "Time": 124937,
    "X": 858,
    "Y": 450,
    "Delta": null,
    "KeyCode": null
  },
  {
    "Type": "MouseMove",
    "Time": 125166,
    "X": 870,
    "Y": 444,
    "Delta": null,
    "KeyCode": null
  },
  {
    "Type": "MouseMove",
    "Time": 125187,
    "X": 882,
    "Y": 441,
    "Delta": null,
    "KeyCode": null
  },
  {
    "Type": "MouseMove",
    "Time": 125195,
    "X": 885,
    "Y": 438,
    "Delta": null,
    "KeyCode": null
  },
  {
    "Type": "MouseMove",
    "Time": 125203,
    "X": 888,
    "Y": 438,
    "Delta": null,
    "KeyCode": null
  },
  {
    "Type": "MouseMove",
    "Time": 125231,
    "X": 897,
    "Y": 435,
    "Delta": null,
    "KeyCode": null
  },
  {
    "Type": "MouseMove",
    "Time": 125253,
    "X": 903,
    "Y": 432,
    "Delta": null,
    "KeyCode": null
  },
  {
    "Type": "MouseMove",
    "Time": 125276,
    "X": 906,
    "Y": 432,
    "Delta": null,
    "KeyCode": null
  },
  {
    "Type": "MouseMove",
    "Time": 125712,
    "X": 903,
    "Y": 429,
    "Delta": null,
    "KeyCode": null
  },
  {
    "Type": "MouseMove",
    "Time": 125745,
    "X": 900,
    "Y": 426,
    "Delta": null,
    "KeyCode": null
  },
  {
    "Type": "MouseMove",
    "Time": 125828,
    "X": 897,
    "Y": 423,
    "Delta": null,
    "KeyCode": null
  },
  {
    "Type": "MouseMove",
    "Time": 126360,
    "X": 897,
    "Y": 426,
    "Delta": null,
    "KeyCode": null
  },
  {
    "Type": "DragStart",
    "Time": 126685,
    "X": 897,
    "Y": 426,
    "Delta": null,
    "KeyCode": null
  },
  {
    "Type": "DragEnd",
    "Time": 126772,
    "X": 897,
    "Y": 426,
    "Delta": null,
    "KeyCode": null
  },
  {
    "Type": "MouseMove",
    "Time": 127295,
    "X": 894,
    "Y": 426,
    "Delta": null,
    "KeyCode": null
  },
  {
    "Type": "MouseMove",
    "Time": 127323,
    "X": 888,
    "Y": 429,
    "Delta": null,
    "KeyCode": null
  },
  {
    "Type": "MouseMove",
    "Time": 127325,
    "X": 885,
    "Y": 432,
    "Delta": null,
    "KeyCode": null
  },
  {
    "Type": "MouseMove",
    "Time": 127335,
    "X": 882,
    "Y": 432,
    "Delta": null,
    "KeyCode": null
  },
  {
    "Type": "MouseMove",
    "Time": 127590,
    "X": 885,
    "Y": 432,
    "Delta": null,
    "KeyCode": null
  },
  {
    "Type": "MouseMove",
    "Time": 127688,
    "X": 888,
    "Y": 432,
    "Delta": null,
    "KeyCode": null
  },
  {
    "Type": "MouseMove",
    "Time": 127726,
    "X": 891,
    "Y": 432,
    "Delta": null,
    "KeyCode": null
  },
  {
    "Type": "MouseMove",
    "Time": 127980,
    "X": 894,
    "Y": 432,
    "Delta": null,
    "KeyCode": null
  },
  {
    "Type": "DragStart",
    "Time": 128204,
    "X": 894,
    "Y": 432,
    "Delta": null,
    "KeyCode": null
  },
  {
    "Type": "DragEnd",
    "Time": 128288,
    "X": 894,
    "Y": 432,
    "Delta": null,
    "KeyCode": null
  },
  {
    "Type": "MouseMove",
    "Time": 128397,
    "X": 888,
    "Y": 444,
    "Delta": null,
    "KeyCode": null
  },
  {
    "Type": "MouseMove",
    "Time": 128419,
    "X": 879,
    "Y": 453,
    "Delta": null,
    "KeyCode": null
  },
  {
    "Type": "MouseMove",
    "Time": 128440,
    "X": 873,
    "Y": 459,
    "Delta": null,
    "KeyCode": null
  },
  {
    "Type": "MouseMove",
    "Time": 128441,
    "X": 870,
    "Y": 462,
    "Delta": null,
    "KeyCode": null
  },
  {
    "Type": "MouseMove",
    "Time": 128449,
    "X": 867,
    "Y": 465,
    "Delta": null,
    "KeyCode": null
  },
  {
    "Type": "MouseMove",
    "Time": 128477,
    "X": 858,
    "Y": 471,
    "Delta": null,
    "KeyCode": null
  },
  {
    "Type": "MouseMove",
    "Time": 128481,
    "X": 855,
    "Y": 474,
    "Delta": null,
    "KeyCode": null
  },
  {
    "Type": "MouseMove",
    "Time": 128505,
    "X": 840,
    "Y": 483,
    "Delta": null,
    "KeyCode": null
  },
  {
    "Type": "MouseMove",
    "Time": 128527,
    "X": 825,
    "Y": 489,
    "Delta": null,
    "KeyCode": null
  },
  {
    "Type": "MouseMove",
    "Time": 128529,
    "X": 819,
    "Y": 495,
    "Delta": null,
    "KeyCode": null
  },
  {
    "Type": "MouseMove",
    "Time": 128555,
    "X": 795,
    "Y": 504,
    "Delta": null,
    "KeyCode": null
  },
  {
    "Type": "MouseMove",
    "Time": 128577,
    "X": 774,
    "Y": 510,
    "Delta": null,
    "KeyCode": null
  },
  {
    "Type": "MouseMove",
    "Time": 128605,
    "X": 765,
    "Y": 516,
    "Delta": null,
    "KeyCode": null
  },
  {
    "Type": "MouseMove",
    "Time": 128626,
    "X": 756,
    "Y": 516,
    "Delta": null,
    "KeyCode": null
  },
  {
    "Type": "MouseMove",
    "Time": 128649,
    "X": 750,
    "Y": 516,
    "Delta": null,
    "KeyCode": null
  },
  {
    "Type": "MouseMove",
    "Time": 128673,
    "X": 738,
    "Y": 522,
    "Delta": null,
    "KeyCode": null
  },
  {
    "Type": "MouseMove",
    "Time": 128695,
    "X": 726,
    "Y": 522,
    "Delta": null,
    "KeyCode": null
  },
  {
    "Type": "MouseMove",
    "Time": 128715,
    "X": 720,
    "Y": 522,
    "Delta": null,
    "KeyCode": null
  },
  {
    "Type": "MouseMove",
    "Time": 128723,
    "X": 717,
    "Y": 525,
    "Delta": null,
    "KeyCode": null
  },
  {
    "Type": "MouseMove",
    "Time": 128739,
    "X": 714,
    "Y": 525,
    "Delta": null,
    "KeyCode": null
  },
  {
    "Type": "MouseMove",
    "Time": 128773,
    "X": 711,
    "Y": 525,
    "Delta": null,
    "KeyCode": null
  },
  {
    "Type": "MouseMove",
    "Time": 128805,
    "X": 705,
    "Y": 525,
    "Delta": null,
    "KeyCode": null
  },
  {
    "Type": "MouseMove",
    "Time": 128827,
    "X": 693,
    "Y": 528,
    "Delta": null,
    "KeyCode": null
  },
  {
    "Type": "MouseMove",
    "Time": 128849,
    "X": 681,
    "Y": 534,
    "Delta": null,
    "KeyCode": null
  },
  {
    "Type": "MouseMove",
    "Time": 128870,
    "X": 663,
    "Y": 537,
    "Delta": null,
    "KeyCode": null
  },
  {
    "Type": "MouseMove",
    "Time": 128875,
    "X": 657,
    "Y": 540,
    "Delta": null,
    "KeyCode": null
  },
  {
    "Type": "MouseMove",
    "Time": 128903,
    "X": 642,
    "Y": 543,
    "Delta": null,
    "KeyCode": null
  },
  {
    "Type": "MouseMove",
    "Time": 128907,
    "X": 639,
    "Y": 543,
    "Delta": null,
    "KeyCode": null
  },
  {
    "Type": "MouseMove",
    "Time": 128945,
    "X": 630,
    "Y": 549,
    "Delta": null,
    "KeyCode": null
  },
  {
    "Type": "MouseMove",
    "Time": 128968,
    "X": 621,
    "Y": 555,
    "Delta": null,
    "KeyCode": null
  },
  {
    "Type": "MouseMove",
    "Time": 128990,
    "X": 606,
    "Y": 561,
    "Delta": null,
    "KeyCode": null
  },
  {
    "Type": "MouseMove",
    "Time": 129012,
    "X": 600,
    "Y": 564,
    "Delta": null,
    "KeyCode": null
  },
  {
    "Type": "MouseMove",
    "Time": 129033,
    "X": 591,
    "Y": 570,
    "Delta": null,
    "KeyCode": null
  },
  {
    "Type": "MouseMove",
    "Time": 129045,
    "X": 585,
    "Y": 573,
    "Delta": null,
    "KeyCode": null
  },
  {
    "Type": "MouseMove",
    "Time": 129059,
    "X": 582,
    "Y": 576,
    "Delta": null,
    "KeyCode": null
  },
  {
    "Type": "MouseMove",
    "Time": 129061,
    "X": 576,
    "Y": 579,
    "Delta": null,
    "KeyCode": null
  },
  {
    "Type": "MouseMove",
    "Time": 129069,
    "X": 573,
    "Y": 582,
    "Delta": null,
    "KeyCode": null
  },
  {
    "Type": "MouseMove",
    "Time": 129093,
    "X": 561,
    "Y": 588,
    "Delta": null,
    "KeyCode": null
  },
  {
    "Type": "MouseMove",
    "Time": 129115,
    "X": 555,
    "Y": 591,
    "Delta": null,
    "KeyCode": null
  },
  {
    "Type": "MouseMove",
    "Time": 129138,
    "X": 555,
    "Y": 594,
    "Delta": null,
    "KeyCode": null
  },
  {
    "Type": "MouseMove",
    "Time": 129251,
    "X": 552,
    "Y": 594,
    "Delta": null,
    "KeyCode": null
  },
  {
    "Type": "MouseMove",
    "Time": 129316,
    "X": 552,
    "Y": 597,
    "Delta": null,
    "KeyCode": null
  },
  {
    "Type": "MouseMove",
    "Time": 129362,
    "X": 549,
    "Y": 603,
    "Delta": null,
    "KeyCode": null
  },
  {
    "Type": "MouseMove",
    "Time": 129383,
    "X": 549,
    "Y": 606,
    "Delta": null,
    "KeyCode": null
  },
  {
    "Type": "MouseMove",
    "Time": 129405,
    "X": 546,
    "Y": 609,
    "Delta": null,
    "KeyCode": null
  }
]